counter_mod6/counter_mod6.v
module counter_mod6(clk, reset, count_out);
  input clk, reset;
  output [2:0] count_out;
  
  reg [2:0] count;

  always @(posedge clk or posedge reset)
  begin
    if (reset)
      count <= 3'b000;
    else if (count == 3'b110)
      count <= 3'b000;
    else
      count <= count + 1;
  end

  assign count_out = count;
endmodule

counter_mod6/test_counter_mod6.v
module test_counter_mod6;

  reg clk;
  reg reset;
  wire [2:0] count_out;

  // Instantiate the module under test
  counter_mod6 dut (
    .clk(clk),
    .reset(reset),
    .count_out(count_out)
  );

  // Clock generation
  always begin
    #5 clk = ~clk; // Toggle the clock every 5 time units (adjust as needed)
  end

  initial begin
    // Initialize signals
    clk = 0;
    reset = 0;

    // Start simulation
    $dumpfile("waveform.vcd"); // Specify the waveform file name
    $dumpvars(0, test_counter_mod6);  // Dump all variables

    // Reset the counter
    reset = 1;
    #10 reset = 0;

    // Simulate for some time
    #500;

    // Stop simulation
    $finish;
  end

endmodule

counter_mod6/waveform.vcd
$date
	Sat Sep 23 16:57:22 2023
$end
$version
	Icarus Verilog
$end
$timescale
	1s
$end
$scope module test_counter_mod6 $end
$var wire 3 ! count_out [2:0] $end
$var reg 1 " clk $end
$var reg 1 # reset $end
$scope module dut $end
$var wire 1 " clk $end
$var wire 3 $ count_out [2:0] $end
$var wire 1 # reset $end
$var reg 3 % count [2:0] $end
$upscope $end
$upscope $end
$enddefinitions $end
$comment Show the parameter values. $end
$dumpall
$end
#0
$dumpvars
b0 %
b0 $
1#
0"
b0 !
$end
#5
1"
#10
0"
0#
#15
b1 !
b1 $
b1 %
1"
#20
0"
#25
b10 !
b10 $
b10 %
1"
#30
0"
#35
b11 !
b11 $
b11 %
1"
#40
0"
#45
b100 !
b100 $
b100 %
1"
#50
0"
#55
b101 !
b101 $
b101 %
1"
#60
0"
#65
b110 !
b110 $
b110 %
1"
#70
0"
#75
b0 !
b0 $
b0 %
1"
#80
0"
#85
b1 !
b1 $
b1 %
1"
#90
0"
#95
b10 !
b10 $
b10 %
1"
#100
0"
#105
b11 !
b11 $
b11 %
1"
#110
0"
#115
b100 !
b100 $
b100 %
1"
#120
0"
#125
b101 !
b101 $
b101 %
1"
#130
0"
#135
b110 !
b110 $
b110 %
1"
#140
0"
#145
b0 !
b0 $
b0 %
1"
#150
0"
#155
b1 !
b1 $
b1 %
1"
#160
0"
#165
b10 !
b10 $
b10 %
1"
#170
0"
#175
b11 !
b11 $
b11 %
1"
#180
0"
#185
b100 !
b100 $
b100 %
1"
#190
0"
#195
b101 !
b101 $
b101 %
1"
#200
0"
#205
b110 !
b110 $
b110 %
1"
#210
0"
#215
b0 !
b0 $
b0 %
1"
#220
0"
#225
b1 !
b1 $
b1 %
1"
#230
0"
#235
b10 !
b10 $
b10 %
1"
#240
0"
#245
b11 !
b11 $
b11 %
1"
#250
0"
#255
b100 !
b100 $
b100 %
1"
#260
0"
#265
b101 !
b101 $
b101 %
1"
#270
0"
#275
b110 !
b110 $
b110 %
1"
#280
0"
#285
b0 !
b0 $
b0 %
1"
#290
0"
#295
b1 !
b1 $
b1 %
1"
#300
0"
#305
b10 !
b10 $
b10 %
1"
#310
0"
#315
b11 !
b11 $
b11 %
1"
#320
0"
#325
b100 !
b100 $
b100 %
1"
#330
0"
#335
b101 !
b101 $
b101 %
1"
#340
0"
#345
b110 !
b110 $
b110 %
1"
#350
0"
#355
b0 !
b0 $
b0 %
1"
#360
0"
#365
b1 !
b1 $
b1 %
1"
#370
0"
#375
b10 !
b10 $
b10 %
1"
#380
0"
#385
b11 !
b11 $
b11 %
1"
#390
0"
#395
b100 !
b100 $
b100 %
1"
#400
0"
#405
b101 !
b101 $
b101 %
1"
#410
0"
#415
b110 !
b110 $
b110 %
1"
#420
0"
#425
b0 !
b0 $
b0 %
1"
#430
0"
#435
b1 !
b1 $
b1 %
1"
#440
0"
#445
b10 !
b10 $
b10 %
1"
#450
0"
#455
b11 !
b11 $
b11 %
1"
#460
0"
#465
b100 !
b100 $
b100 %
1"
#470
0"
#475
b101 !
b101 $
b101 %
1"
#480
0"
#485
b110 !
b110 $
b110 %
1"
#490
0"
#495
b0 !
b0 $
b0 %
1"
#500
0"
#505
b1 !
b1 $
b1 %
1"
