respostas/Q3/timer/counter_mod10.v
module counter_mod10 (
  input wire clk,
  input wire clear,
  input wire load,
  input wire stop,
  output wire tc,
  output wire zero,
  input wire [3:0] bcd_digit_input,
  output wire [3:0] bcd_digit_output
);

  reg [3:0] bcd_digit_reg; // Register to hold the BCD digit value

  always @(posedge clk) begin
    if (clear) begin
      bcd_digit_reg <= 4'b0000;
    end else if (!stop) begin
      if (load) begin
        bcd_digit_reg <= bcd_digit_input;
      end else begin
        if (bcd_digit_reg == 4'b0000) begin
          bcd_digit_reg <= 4'b1001; // Load 9 when it rolls over from 0
        end else begin
          bcd_digit_reg <= bcd_digit_reg - 1;
        end
      end
    end
  end

  assign bcd_digit_output = bcd_digit_reg;
  assign zero = (bcd_digit_output == 4'b0000);
  assign tc = zero;

endmodule

respostas/Q3/timer/test_counter_mod10.v
module test_counter_mod10;

  reg clk;
  reg clear;
  reg load;
  reg stop;
  wire tc;
  wire zero;
  reg [3:0] bcd_digit_input;
  wire [3:0] bcd_digit_output;

  // Instantiate the counter_mod10 module under test
  counter_mod10 dut (
    .clk(clk),
    .clear(clear),
    .load(load),
    .stop(stop),
    .tc(tc),
    .zero(zero),
    .bcd_digit_input(bcd_digit_input),
    .bcd_digit_output(bcd_digit_output)
  );

  // Clock generation
  always begin
    #5 clk = ~clk; // Toggle the clock every 5 time units (adjust as needed)
  end

  initial begin
    $dumpfile("counter_mod10.vcd"); // Specify the waveform file name
    $dumpvars(0, test_counter_mod10);  // Dump all variables
    
    // Initialize signals
    clk = 0;
    clear = 0;
    load = 0;
    stop = 0;
    bcd_digit_input = 4'b0000;

    // Start simulation
   
    

    // Clear the counter initially
    clear = 1;
    #10 clear = 0;

    // Simulate for some time
    #100; // Adjust the simulation time as needed

    // Load a new value into the counter
    load = 1;
    bcd_digit_input = 4'b0101; // Load BCD 5
    #10 load = 0;

    // Allow the counter to run
    #2000; // Adjust the simulation time as needed

    // Stop the counter when the output becomes 4'b0000
    #10 if (bcd_digit_output == 4'b0000) stop = 1;

    // Simulate for some more time
    #500; // Adjust the simulation time as needed

    // Stop simulation
    $finish;
  end

endmodule

respostas/Q3/timer/counter_mod10.vcd
$date
	Sun Sep 24 11:01:39 2023
$end
$version
	Icarus Verilog
$end
$timescale
	1s
$end
$scope module test_counter_mod10 $end
$var wire 1 ! zero $end
$var wire 1 " tc $end
$var wire 4 # bcd_digit_output [3:0] $end
$var reg 4 $ bcd_digit_input [3:0] $end
$var reg 1 % clear $end
$var reg 1 & clk $end
$var reg 1 ' load $end
$var reg 1 ( stop $end
$scope module dut $end
$var wire 4 ) bcd_digit_input [3:0] $end
$var wire 1 % clear $end
$var wire 1 & clk $end
$var wire 1 ' load $end
$var wire 1 ( stop $end
$var wire 1 " tc $end
$var wire 1 ! zero $end
$var wire 4 * bcd_digit_output [3:0] $end
$var reg 4 + bcd_digit_reg [3:0] $end
$upscope $end
$upscope $end
$enddefinitions $end
$comment Show the parameter values. $end
$dumpall
$end
#0
$dumpvars
bx +
bx *
b0 )
0(
0'
0&
1%
b0 $
bx #
x"
x!
$end
#5
1"
1!
b0 #
b0 *
b0 +
1&
#10
0&
0%
#15
0"
0!
b1001 #
b1001 *
b1001 +
1&
#20
0&
#25
b1000 #
b1000 *
b1000 +
1&
#30
0&
#35
b111 #
b111 *
b111 +
1&
#40
0&
#45
b110 #
b110 *
b110 +
1&
#50
0&
#55
b101 #
b101 *
b101 +
1&
#60
0&
#65
b100 #
b100 *
b100 +
1&
#70
0&
#75
b11 #
b11 *
b11 +
1&
#80
0&
#85
b10 #
b10 *
b10 +
1&
#90
0&
#95
b1 #
b1 *
b1 +
1&
#100
0&
#105
1"
1!
b0 #
b0 *
b0 +
1&
#110
0&
b101 $
b101 )
1'
#115
0"
0!
b101 #
b101 *
b101 +
1&
#120
0&
0'
#125
b100 #
b100 *
b100 +
1&
#130
0&
#135
b11 #
b11 *
b11 +
1&
#140
0&
#145
b10 #
b10 *
b10 +
1&
#150
0&
#155
b1 #
b1 *
b1 +
1&
#160
0&
#165
1"
1!
b0 #
b0 *
b0 +
1&
#170
0&
#175
0"
0!
b1001 #
b1001 *
b1001 +
1&
#180
0&
#185
b1000 #
b1000 *
b1000 +
1&
#190
0&
#195
b111 #
b111 *
b111 +
1&
#200
0&
#205
b110 #
b110 *
b110 +
1&
#210
0&
#215
b101 #
b101 *
b101 +
1&
#220
0&
#225
b100 #
b100 *
b100 +
1&
#230
0&
#235
b11 #
b11 *
b11 +
1&
#240
0&
#245
b10 #
b10 *
b10 +
1&
#250
0&
#255
b1 #
b1 *
b1 +
1&
#260
0&
#265
1"
1!
b0 #
b0 *
b0 +
1&
#270
0&
#275
0"
0!
b1001 #
b1001 *
b1001 +
1&
#280
0&
#285
b1000 #
b1000 *
b1000 +
1&
#290
0&
#295
b111 #
b111 *
b111 +
1&
#300
0&
#305
b110 #
b110 *
b110 +
1&
#310
0&
#315
b101 #
b101 *
b101 +
1&
#320
0&
#325
b100 #
b100 *
b100 +
1&
#330
0&
#335
b11 #
b11 *
b11 +
1&
#340
0&
#345
b10 #
b10 *
b10 +
1&
#350
0&
#355
b1 #
b1 *
b1 +
1&
#360
0&
#365
1"
1!
b0 #
b0 *
b0 +
1&
#370
0&
#375
0"
0!
b1001 #
b1001 *
b1001 +
1&
#380
0&
#385
b1000 #
b1000 *
b1000 +
1&
#390
0&
#395
b111 #
b111 *
b111 +
1&
#400
0&
#405
b110 #
b110 *
b110 +
1&
#410
0&
#415
b101 #
b101 *
b101 +
1&
#420
0&
#425
b100 #
b100 *
b100 +
1&
#430
0&
#435
b11 #
b11 *
b11 +
1&
#440
0&
#445
b10 #
b10 *
b10 +
1&
#450
0&
#455
b1 #
b1 *
b1 +
1&
#460
0&
#465
1"
1!
b0 #
b0 *
b0 +
1&
#470
0&
#475
0"
0!
b1001 #
b1001 *
b1001 +
1&
#480
0&
#485
b1000 #
b1000 *
b1000 +
1&
#490
0&
#495
b111 #
b111 *
b111 +
1&
#500
0&
#505
b110 #
b110 *
b110 +
1&
#510
0&
#515
b101 #
b101 *
b101 +
1&
#520
0&
#525
b100 #
b100 *
b100 +
1&
#530
0&
#535
b11 #
b11 *
b11 +
1&
#540
0&
#545
b10 #
b10 *
b10 +
1&
#550
0&
#555
b1 #
b1 *
b1 +
1&
#560
0&
#565
1"
1!
b0 #
b0 *
b0 +
1&
#570
0&
#575
0"
0!
b1001 #
b1001 *
b1001 +
1&
#580
0&
#585
b1000 #
b1000 *
b1000 +
1&
#590
0&
#595
b111 #
b111 *
b111 +
1&
#600
0&
#605
b110 #
b110 *
b110 +
1&
#610
0&
#615
b101 #
b101 *
b101 +
1&
#620
0&
#625
b100 #
b100 *
b100 +
1&
#630
0&
#635
b11 #
b11 *
b11 +
1&
#640
0&
#645
b10 #
b10 *
b10 +
1&
#650
0&
#655
b1 #
b1 *
b1 +
1&
#660
0&
#665
1"
1!
b0 #
b0 *
b0 +
1&
#670
0&
#675
0"
0!
b1001 #
b1001 *
b1001 +
1&
#680
0&
#685
b1000 #
b1000 *
b1000 +
1&
#690
0&
#695
b111 #
b111 *
b111 +
1&
#700
0&
#705
b110 #
b110 *
b110 +
1&
#710
0&
#715
b101 #
b101 *
b101 +
1&
#720
0&
#725
b100 #
b100 *
b100 +
1&
#730
0&
#735
b11 #
b11 *
b11 +
1&
#740
0&
#745
b10 #
b10 *
b10 +
1&
#750
0&
#755
b1 #
b1 *
b1 +
1&
#760
0&
#765
1"
1!
b0 #
b0 *
b0 +
1&
#770
0&
#775
0"
0!
b1001 #
b1001 *
b1001 +
1&
#780
0&
#785
b1000 #
b1000 *
b1000 +
1&
#790
0&
#795
b111 #
b111 *
b111 +
1&
#800
0&
#805
b110 #
b110 *
b110 +
1&
#810
0&
#815
b101 #
b101 *
b101 +
1&
#820
0&
#825
b100 #
b100 *
b100 +
1&
#830
0&
#835
b11 #
b11 *
b11 +
1&
#840
0&
#845
b10 #
b10 *
b10 +
1&
#850
0&
#855
b1 #
b1 *
b1 +
1&
#860
0&
#865
1"
1!
b0 #
b0 *
b0 +
1&
#870
0&
#875
0"
0!
b1001 #
b1001 *
b1001 +
1&
#880
0&
#885
b1000 #
b1000 *
b1000 +
1&
#890
0&
#895
b111 #
b111 *
b111 +
1&
#900
0&
#905
b110 #
b110 *
b110 +
1&
#910
0&
#915
b101 #
b101 *
b101 +
1&
#920
0&
#925
b100 #
b100 *
b100 +
1&
#930
0&
#935
b11 #
b11 *
b11 +
1&
#940
0&
#945
b10 #
b10 *
b10 +
1&
#950
0&
#955
b1 #
b1 *
b1 +
1&
#960
0&
#965
1"
1!
b0 #
b0 *
b0 +
1&
#970
0&
#975
0"
0!
b1001 #
b1001 *
b1001 +
1&
#980
0&
#985
b1000 #
b1000 *
b1000 +
1&
#990
0&
#995
b111 #
b111 *
b111 +
1&
#1000
0&
#1005
b110 #
b110 *
b110 +
1&
#1010
0&
#1015
b101 #
b101 *
b101 +
1&
#1020
0&
#1025
b100 #
b100 *
b100 +
1&
#1030
0&
#1035
b11 #
b11 *
b11 +
1&
#1040
0&
#1045
b10 #
b10 *
b10 +
1&
#1050
0&
#1055
b1 #
b1 *
b1 +
1&
#1060
0&
#1065
1"
1!
b0 #
b0 *
b0 +
1&
#1070
0&
#1075
0"
0!
b1001 #
b1001 *
b1001 +
1&
#1080
0&
#1085
b1000 #
b1000 *
b1000 +
1&
#1090
0&
#1095
b111 #
b111 *
b111 +
1&
#1100
0&
#1105
b110 #
b110 *
b110 +
1&
#1110
0&
#1115
b101 #
b101 *
b101 +
1&
#1120
0&
#1125
b100 #
b100 *
b100 +
1&
#1130
0&
#1135
b11 #
b11 *
b11 +
1&
#1140
0&
#1145
b10 #
b10 *
b10 +
1&
#1150
0&
#1155
b1 #
b1 *
b1 +
1&
#1160
0&
#1165
1"
1!
b0 #
b0 *
b0 +
1&
#1170
0&
#1175
0"
0!
b1001 #
b1001 *
b1001 +
1&
#1180
0&
#1185
b1000 #
b1000 *
b1000 +
1&
#1190
0&
#1195
b111 #
b111 *
b111 +
1&
#1200
0&
#1205
b110 #
b110 *
b110 +
1&
#1210
0&
#1215
b101 #
b101 *
b101 +
1&
#1220
0&
#1225
b100 #
b100 *
b100 +
1&
#1230
0&
#1235
b11 #
b11 *
b11 +
1&
#1240
0&
#1245
b10 #
b10 *
b10 +
1&
#1250
0&
#1255
b1 #
b1 *
b1 +
1&
#1260
0&
#1265
1"
1!
b0 #
b0 *
b0 +
1&
#1270
0&
#1275
0"
0!
b1001 #
b1001 *
b1001 +
1&
#1280
0&
#1285
b1000 #
b1000 *
b1000 +
1&
#1290
0&
#1295
b111 #
b111 *
b111 +
1&
#1300
0&
#1305
b110 #
b110 *
b110 +
1&
#1310
0&
#1315
b101 #
b101 *
b101 +
1&
#1320
0&
#1325
b100 #
b100 *
b100 +
1&
#1330
0&
#1335
b11 #
b11 *
b11 +
1&
#1340
0&
#1345
b10 #
b10 *
b10 +
1&
#1350
0&
#1355
b1 #
b1 *
b1 +
1&
#1360
0&
#1365
1"
1!
b0 #
b0 *
b0 +
1&
#1370
0&
#1375
0"
0!
b1001 #
b1001 *
b1001 +
1&
#1380
0&
#1385
b1000 #
b1000 *
b1000 +
1&
#1390
0&
#1395
b111 #
b111 *
b111 +
1&
#1400
0&
#1405
b110 #
b110 *
b110 +
1&
#1410
0&
#1415
b101 #
b101 *
b101 +
1&
#1420
0&
#1425
b100 #
b100 *
b100 +
1&
#1430
0&
#1435
b11 #
b11 *
b11 +
1&
#1440
0&
#1445
b10 #
b10 *
b10 +
1&
#1450
0&
#1455
b1 #
b1 *
b1 +
1&
#1460
0&
#1465
1"
1!
b0 #
b0 *
b0 +
1&
#1470
0&
#1475
0"
0!
b1001 #
b1001 *
b1001 +
1&
#1480
0&
#1485
b1000 #
b1000 *
b1000 +
1&
#1490
0&
#1495
b111 #
b111 *
b111 +
1&
#1500
0&
#1505
b110 #
b110 *
b110 +
1&
#1510
0&
#1515
b101 #
b101 *
b101 +
1&
#1520
0&
#1525
b100 #
b100 *
b100 +
1&
#1530
0&
#1535
b11 #
b11 *
b11 +
1&
#1540
0&
#1545
b10 #
b10 *
b10 +
1&
#1550
0&
#1555
b1 #
b1 *
b1 +
1&
#1560
0&
#1565
1"
1!
b0 #
b0 *
b0 +
1&
#1570
0&
#1575
0"
0!
b1001 #
b1001 *
b1001 +
1&
#1580
0&
#1585
b1000 #
b1000 *
b1000 +
1&
#1590
0&
#1595
b111 #
b111 *
b111 +
1&
#1600
0&
#1605
b110 #
b110 *
b110 +
1&
#1610
0&
#1615
b101 #
b101 *
b101 +
1&
#1620
0&
#1625
b100 #
b100 *
b100 +
1&
#1630
0&
#1635
b11 #
b11 *
b11 +
1&
#1640
0&
#1645
b10 #
b10 *
b10 +
1&
#1650
0&
#1655
b1 #
b1 *
b1 +
1&
#1660
0&
#1665
1"
1!
b0 #
b0 *
b0 +
1&
#1670
0&
#1675
0"
0!
b1001 #
b1001 *
b1001 +
1&
#1680
0&
#1685
b1000 #
b1000 *
b1000 +
1&
#1690
0&
#1695
b111 #
b111 *
b111 +
1&
#1700
0&
#1705
b110 #
b110 *
b110 +
1&
#1710
0&
#1715
b101 #
b101 *
b101 +
1&
#1720
0&
#1725
b100 #
b100 *
b100 +
1&
#1730
0&
#1735
b11 #
b11 *
b11 +
1&
#1740
0&
#1745
b10 #
b10 *
b10 +
1&
#1750
0&
#1755
b1 #
b1 *
b1 +
1&
#1760
0&
#1765
1"
1!
b0 #
b0 *
b0 +
1&
#1770
0&
#1775
0"
0!
b1001 #
b1001 *
b1001 +
1&
#1780
0&
#1785
b1000 #
b1000 *
b1000 +
1&
#1790
0&
#1795
b111 #
b111 *
b111 +
1&
#1800
0&
#1805
b110 #
b110 *
b110 +
1&
#1810
0&
#1815
b101 #
b101 *
b101 +
1&
#1820
0&
#1825
b100 #
b100 *
b100 +
1&
#1830
0&
#1835
b11 #
b11 *
b11 +
1&
#1840
0&
#1845
b10 #
b10 *
b10 +
1&
#1850
0&
#1855
b1 #
b1 *
b1 +
1&
#1860
0&
#1865
1"
1!
b0 #
b0 *
b0 +
1&
#1870
0&
#1875
0"
0!
b1001 #
b1001 *
b1001 +
1&
#1880
0&
#1885
b1000 #
b1000 *
b1000 +
1&
#1890
0&
#1895
b111 #
b111 *
b111 +
1&
#1900
0&
#1905
b110 #
b110 *
b110 +
1&
#1910
0&
#1915
b101 #
b101 *
b101 +
1&
#1920
0&
#1925
b100 #
b100 *
b100 +
1&
#1930
0&
#1935
b11 #
b11 *
b11 +
1&
#1940
0&
#1945
b10 #
b10 *
b10 +
1&
#1950
0&
#1955
b1 #
b1 *
b1 +
1&
#1960
0&
#1965
1"
1!
b0 #
b0 *
b0 +
1&
#1970
0&
#1975
0"
0!
b1001 #
b1001 *
b1001 +
1&
#1980
0&
#1985
b1000 #
b1000 *
b1000 +
1&
#1990
0&
#1995
b111 #
b111 *
b111 +
1&
#2000
0&
#2005
b110 #
b110 *
b110 +
1&
#2010
0&
#2015
b101 #
b101 *
b101 +
1&
#2020
0&
#2025
b100 #
b100 *
b100 +
1&
#2030
0&
#2035
b11 #
b11 *
b11 +
1&
#2040
0&
#2045
b10 #
b10 *
b10 +
1&
#2050
0&
#2055
b1 #
b1 *
b1 +
1&
#2060
0&
#2065
1"
1!
b0 #
b0 *
b0 +
1&
#2070
0&
#2075
0"
0!
b1001 #
b1001 *
b1001 +
1&
#2080
0&
#2085
b1000 #
b1000 *
b1000 +
1&
#2090
0&
#2095
b111 #
b111 *
b111 +
1&
#2100
0&
#2105
b110 #
b110 *
b110 +
1&
#2110
0&
#2115
b101 #
b101 *
b101 +
1&
#2120
0&
#2125
b100 #
b100 *
b100 +
1&
#2130
0&
#2135
b11 #
b11 *
b11 +
1&
#2140
0&
#2145
b10 #
b10 *
b10 +
1&
#2150
0&
#2155
b1 #
b1 *
b1 +
1&
#2160
0&
#2165
1"
1!
b0 #
b0 *
b0 +
1&
#2170
0&
#2175
0"
0!
b1001 #
b1001 *
b1001 +
1&
#2180
0&
#2185
b1000 #
b1000 *
b1000 +
1&
#2190
0&
#2195
b111 #
b111 *
b111 +
1&
#2200
0&
#2205
b110 #
b110 *
b110 +
1&
#2210
0&
#2215
b101 #
b101 *
b101 +
1&
#2220
0&
#2225
b100 #
b100 *
b100 +
1&
#2230
0&
#2235
b11 #
b11 *
b11 +
1&
#2240
0&
#2245
b10 #
b10 *
b10 +
1&
#2250
0&
#2255
b1 #
b1 *
b1 +
1&
#2260
0&
#2265
1"
1!
b0 #
b0 *
b0 +
1&
#2270
0&
#2275
0"
0!
b1001 #
b1001 *
b1001 +
1&
#2280
0&
#2285
b1000 #
b1000 *
b1000 +
1&
#2290
0&
#2295
b111 #
b111 *
b111 +
1&
#2300
0&
#2305
b110 #
b110 *
b110 +
1&
#2310
0&
#2315
b101 #
b101 *
b101 +
1&
#2320
0&
#2325
b100 #
b100 *
b100 +
1&
#2330
0&
#2335
b11 #
b11 *
b11 +
1&
#2340
0&
#2345
b10 #
b10 *
b10 +
1&
#2350
0&
#2355
b1 #
b1 *
b1 +
1&
#2360
0&
#2365
1"
1!
b0 #
b0 *
b0 +
1&
#2370
0&
#2375
0"
0!
b1001 #
b1001 *
b1001 +
1&
#2380
0&
#2385
b1000 #
b1000 *
b1000 +
1&
#2390
0&
#2395
b111 #
b111 *
b111 +
1&
#2400
0&
#2405
b110 #
b110 *
b110 +
1&
#2410
0&
#2415
b101 #
b101 *
b101 +
1&
#2420
0&
#2425
b100 #
b100 *
b100 +
1&
#2430
0&
#2435
b11 #
b11 *
b11 +
1&
#2440
0&
#2445
b10 #
b10 *
b10 +
1&
#2450
0&
#2455
b1 #
b1 *
b1 +
1&
#2460
0&
#2465
1"
1!
b0 #
b0 *
b0 +
1&
#2470
0&
#2475
0"
0!
b1001 #
b1001 *
b1001 +
1&
#2480
0&
#2485
b1000 #
b1000 *
b1000 +
1&
#2490
0&
#2495
b111 #
b111 *
b111 +
1&
#2500
0&
#2505
b110 #
b110 *
b110 +
1&
#2510
0&
#2515
b101 #
b101 *
b101 +
1&
#2520
0&
#2525
b100 #
b100 *
b100 +
1&
#2530
0&
#2535
b11 #
b11 *
b11 +
1&
#2540
0&
#2545
b10 #
b10 *
b10 +
1&
#2550
0&
#2555
b1 #
b1 *
b1 +
1&
#2560
0&
#2565
1"
1!
b0 #
b0 *
b0 +
1&
#2570
0&
#2575
0"
0!
b1001 #
b1001 *
b1001 +
1&
#2580
0&
#2585
b1000 #
b1000 *
b1000 +
1&
#2590
0&
#2595
b111 #
b111 *
b111 +
1&
#2600
0&
#2605
b110 #
b110 *
b110 +
1&
#2610
0&
#2615
b101 #
b101 *
b101 +
1&
#2620
0&
#2625
b100 #
b100 *
b100 +
1&
