respostas/Q3/timer/counter_mod10.v
module counter_mod10 (
  input wire clk,
  input wire clear,
  input wire load,
  input wire stop,
  output wire tc,
  output wire zero,
  input wire [3:0] bcd_digit_input,
  output wire [3:0] bcd_digit_output
);

  reg [3:0] bcd_digit_reg; // Register to hold the BCD digit value

  always @(posedge clk) begin
    if (clear) begin
      bcd_digit_reg <= 4'b0000;
    end else if (!stop) begin
      if (load) begin
        bcd_digit_reg <= bcd_digit_input;
      end else begin
        if (bcd_digit_reg == 4'b0000) begin
          bcd_digit_reg <= 4'b1001; // Load 9 when it rolls over from 0
        end else begin
          bcd_digit_reg <= bcd_digit_reg - 1;
        end
      end
    end
  end

  assign bcd_digit_output = bcd_digit_reg;
  assign zero = (bcd_digit_output == 4'b0000);
  assign tc = !zero;

endmodule

respostas/Q3/timer/counter_mod6.v
module counter_mod6 (
  input wire clk,
  input wire clear,
  input wire load,
  input wire stop,
  output wire tc,
  output wire zero,
  input wire [3:0] bcd_digit_input,
  output wire [3:0] bcd_digit_output
);


  reg [3:0] bcd_digit_reg; // Register to hold the BCD digit value

  always @(posedge clk) begin
    if (clear) begin
      bcd_digit_reg <= 4'b0000;
    end else if (!stop) begin
      if (load) begin
        bcd_digit_reg <= bcd_digit_input;
      end else begin
        if (bcd_digit_reg == 4'b0000) begin
          bcd_digit_reg <= 4'b0101; // Load 9 when it rolls over from 0
        end else begin
          bcd_digit_reg <= bcd_digit_reg - 1;
        end
      end
    end
  end

  assign bcd_digit_output = bcd_digit_reg;
  assign zero = (bcd_digit_output == 4'b0000);
  assign tc = !zero;

endmodule

respostas/Q3/timer/timer.v
`include "counter_mod10.v"
`include "counter_mod6.v"

module timer (
  input wire clk,
  input wire clear,
  input wire load,
  input wire stop,
  input wire [3:0] bcd_input,
  output wire zero,
  output wire [3:0] bcd_output_usec,
  output wire [3:0] bcd_output_dsec,
  output wire [3:0] bcd_output_min
);

  wire tc_counter_mod10_usec;
  wire tc_counter_mod6_dsec;

  wire zero_counter_mod10_usec;
  wire zero_counter_mod6_dsec;
  wire zero_counter_mod10_min;

  wire [3:0] bcd_digit_output_counter_mod10_usec;
  wire [3:0] bcd_digit_output_counter_mod6_dsec;
  wire [3:0] bcd_digit_output_counter_mod10_min;

  // Instantiate the counter_mod10 module
  counter_mod10 counter_mod10_usec (
    .clk(clk),
    .clear(clear),
    .load(load),
    .stop(stop),
    .tc(tc_counter_mod10_usec),
    .zero(zero_counter_mod10),
    .bcd_digit_input(bcd_input),
    .bcd_digit_output(bcd_digit_output_counter_mod10_usec)
  );

  counter_mod6 counter_mod6_dsec (
    .clk(clk),
    .clear(clear),
    .load(load),
    .stop(tc_counter_mod10_usec),
    .tc(tc_counter_mod6_dsec),
    .zero(zero_counter_mod6_dsec),
    .bcd_digit_input(bcd_digit_output_counter_mod10_usec),
    .bcd_digit_output(bcd_digit_output_counter_mod6_dsec)
  );

  counter_mod10 counter_mod10_min (
    .clk(clk),
    .clear(clear),
    .load(load),
    .stop(tc_counter_mod6_dsec),
    .tc(tc_counter_mod10_min),
    .zero(zero_counter_mod10_min),
    .bcd_digit_input(bcd_digit_output_counter_mod6_dsec),
    .bcd_digit_output(bcd_digit_output_counter_mod10_min)
  );


  assign zero =  zero_counter_mod10_min & zero_counter_mod6_dsec & zero_counter_mod10_usec;

  assign bcd_output_usec = bcd_digit_output_counter_mod10_usec;
  assign bcd_output_dsec = bcd_digit_output_counter_mod6_dsec;
  assign bcd_output_min = bcd_digit_output_counter_mod10_min;


endmodule

respostas/Q3/timer/test_timer.v
module test_timer;

  reg clk;
  reg clear;
  reg load;
  reg stop;
  wire zero;
  wire [3:0] bcd_output_usec;
  wire [3:0] bcd_output_dsec;
  wire [3:0] bcd_output_min;
  reg [3:0] bcd_input;

  // Instantiate the timer module under test
  timer dut (
    .clk(clk),
    .clear(clear),
    .load(load),
    .stop(stop),
    .bcd_input(bcd_input),
    .zero(zero),
    .bcd_output_usec(bcd_output_usec),
    .bcd_output_dsec(bcd_output_dsec),
    .bcd_output_min(bcd_output_min)
  );

  // Instantiate the clock generator
  initial begin
    clk = 0;
    forever #5 clk = ~clk; // Generate clock signal (adjust delay as needed)
  end

  initial begin
    // Initialize signals
    clear = 1;
    load = 0;
    stop = 0;
    bcd_input = 4'b0000;


    // Start simulation
    $dumpfile("timer.vcd"); // Specify the waveform file name
    $dumpvars(0, test_timer);  // Dump all variables

    // Clear the timer initially
    #10 clear = 0;

    // Simulate for some time
    #3000; // Adjust the simulation time as needed

    // Load a new value into the timer

    // Allow the timer to run
    #200; // Adjust the simulation time as needed
    stop = 1;
    #200
    // Stop simulation
    $finish;
  end

endmodule

respostas/Q3/timer/timer.vcd
$date
	Sun Sep 24 12:12:53 2023
$end
$version
	Icarus Verilog
$end
$timescale
	1s
$end
$scope module test_timer $end
$var wire 1 ! zero $end
$var wire 4 " bcd_output_usec [3:0] $end
$var wire 4 # bcd_output_min [3:0] $end
$var wire 4 $ bcd_output_dsec [3:0] $end
$var reg 4 % bcd_input [3:0] $end
$var reg 1 & clear $end
$var reg 1 ' clk $end
$var reg 1 ( load $end
$var reg 1 ) stop $end
$scope module dut $end
$var wire 4 * bcd_input [3:0] $end
$var wire 4 + bcd_output_dsec [3:0] $end
$var wire 4 , bcd_output_min [3:0] $end
$var wire 4 - bcd_output_usec [3:0] $end
$var wire 1 & clear $end
$var wire 1 ' clk $end
$var wire 1 ( load $end
$var wire 1 ) stop $end
$var wire 1 ! zero $end
$var wire 1 . zero_counter_mod10_usec $end
$var wire 1 / zero_counter_mod6_dsec $end
$var wire 1 0 zero_counter_mod10_min $end
$var wire 1 1 zero_counter_mod10 $end
$var wire 1 2 tc_counter_mod6_dsec $end
$var wire 1 3 tc_counter_mod10_usec $end
$var wire 1 4 tc_counter_mod10_min $end
$var wire 4 5 bcd_digit_output_counter_mod6_dsec [3:0] $end
$var wire 4 6 bcd_digit_output_counter_mod10_usec [3:0] $end
$var wire 4 7 bcd_digit_output_counter_mod10_min [3:0] $end
$scope module counter_mod10_min $end
$var wire 1 & clear $end
$var wire 1 ' clk $end
$var wire 1 ( load $end
$var wire 1 0 zero $end
$var wire 1 4 tc $end
$var wire 1 2 stop $end
$var wire 4 8 bcd_digit_output [3:0] $end
$var wire 4 9 bcd_digit_input [3:0] $end
$var reg 4 : bcd_digit_reg [3:0] $end
$upscope $end
$scope module counter_mod10_usec $end
$var wire 4 ; bcd_digit_input [3:0] $end
$var wire 1 & clear $end
$var wire 1 ' clk $end
$var wire 1 ( load $end
$var wire 1 ) stop $end
$var wire 1 1 zero $end
$var wire 1 3 tc $end
$var wire 4 < bcd_digit_output [3:0] $end
$var reg 4 = bcd_digit_reg [3:0] $end
$upscope $end
$scope module counter_mod6_dsec $end
$var wire 4 > bcd_digit_input [3:0] $end
$var wire 1 & clear $end
$var wire 1 ' clk $end
$var wire 1 ( load $end
$var wire 1 3 stop $end
$var wire 1 / zero $end
$var wire 1 2 tc $end
$var wire 4 ? bcd_digit_output [3:0] $end
$var reg 4 @ bcd_digit_reg [3:0] $end
$upscope $end
$upscope $end
$upscope $end
$enddefinitions $end
$comment Show the parameter values. $end
$dumpall
$end
#0
$dumpvars
bx @
bx ?
bx >
bx =
bx <
b0 ;
bx :
bx 9
bx 8
bx 7
bx 6
bx 5
x4
x3
x2
x1
x0
x/
z.
bx -
bx ,
bx +
b0 *
0)
0(
0'
1&
b0 %
bx $
bx #
bx "
x!
$end
#5
03
11
b0 "
b0 -
b0 6
b0 <
b0 =
b0 >
02
1/
b0 $
b0 +
b0 5
b0 9
b0 ?
b0 @
04
10
b0 #
b0 ,
b0 7
b0 8
b0 :
1'
#10
0'
0&
#15
0!
14
00
b1001 #
b1001 ,
b1001 7
b1001 8
b1001 :
12
0/
b101 $
b101 +
b101 5
b101 9
b101 ?
b101 @
13
01
b1001 "
b1001 -
b1001 6
b1001 <
b1001 =
b1001 >
1'
#20
0'
#25
b1000 "
b1000 -
b1000 6
b1000 <
b1000 =
b1000 >
1'
#30
0'
#35
b111 "
b111 -
b111 6
b111 <
b111 =
b111 >
1'
#40
0'
#45
b110 "
b110 -
b110 6
b110 <
b110 =
b110 >
1'
#50
0'
#55
b101 "
b101 -
b101 6
b101 <
b101 =
b101 >
1'
#60
0'
#65
b100 "
b100 -
b100 6
b100 <
b100 =
b100 >
1'
#70
0'
#75
b11 "
b11 -
b11 6
b11 <
b11 =
b11 >
1'
#80
0'
#85
b10 "
b10 -
b10 6
b10 <
b10 =
b10 >
1'
#90
0'
#95
b1 "
b1 -
b1 6
b1 <
b1 =
b1 >
1'
#100
0'
#105
03
11
b0 "
b0 -
b0 6
b0 <
b0 =
b0 >
1'
#110
0'
#115
b100 $
b100 +
b100 5
b100 9
b100 ?
b100 @
13
01
b1001 "
b1001 -
b1001 6
b1001 <
b1001 =
b1001 >
1'
#120
0'
#125
b1000 "
b1000 -
b1000 6
b1000 <
b1000 =
b1000 >
1'
#130
0'
#135
b111 "
b111 -
b111 6
b111 <
b111 =
b111 >
1'
#140
0'
#145
b110 "
b110 -
b110 6
b110 <
b110 =
b110 >
1'
#150
0'
#155
b101 "
b101 -
b101 6
b101 <
b101 =
b101 >
1'
#160
0'
#165
b100 "
b100 -
b100 6
b100 <
b100 =
b100 >
1'
#170
0'
#175
b11 "
b11 -
b11 6
b11 <
b11 =
b11 >
1'
#180
0'
#185
b10 "
b10 -
b10 6
b10 <
b10 =
b10 >
1'
#190
0'
#195
b1 "
b1 -
b1 6
b1 <
b1 =
b1 >
1'
#200
0'
#205
03
11
b0 "
b0 -
b0 6
b0 <
b0 =
b0 >
1'
#210
0'
#215
b11 $
b11 +
b11 5
b11 9
b11 ?
b11 @
13
01
b1001 "
b1001 -
b1001 6
b1001 <
b1001 =
b1001 >
1'
#220
0'
#225
b1000 "
b1000 -
b1000 6
b1000 <
b1000 =
b1000 >
1'
#230
0'
#235
b111 "
b111 -
b111 6
b111 <
b111 =
b111 >
1'
#240
0'
#245
b110 "
b110 -
b110 6
b110 <
b110 =
b110 >
1'
#250
0'
#255
b101 "
b101 -
b101 6
b101 <
b101 =
b101 >
1'
#260
0'
#265
b100 "
b100 -
b100 6
b100 <
b100 =
b100 >
1'
#270
0'
#275
b11 "
b11 -
b11 6
b11 <
b11 =
b11 >
1'
#280
0'
#285
b10 "
b10 -
b10 6
b10 <
b10 =
b10 >
1'
#290
0'
#295
b1 "
b1 -
b1 6
b1 <
b1 =
b1 >
1'
#300
0'
#305
03
11
b0 "
b0 -
b0 6
b0 <
b0 =
b0 >
1'
#310
0'
#315
b10 $
b10 +
b10 5
b10 9
b10 ?
b10 @
13
01
b1001 "
b1001 -
b1001 6
b1001 <
b1001 =
b1001 >
1'
#320
0'
#325
b1000 "
b1000 -
b1000 6
b1000 <
b1000 =
b1000 >
1'
#330
0'
#335
b111 "
b111 -
b111 6
b111 <
b111 =
b111 >
1'
#340
0'
#345
b110 "
b110 -
b110 6
b110 <
b110 =
b110 >
1'
#350
0'
#355
b101 "
b101 -
b101 6
b101 <
b101 =
b101 >
1'
#360
0'
#365
b100 "
b100 -
b100 6
b100 <
b100 =
b100 >
1'
#370
0'
#375
b11 "
b11 -
b11 6
b11 <
b11 =
b11 >
1'
#380
0'
#385
b10 "
b10 -
b10 6
b10 <
b10 =
b10 >
1'
#390
0'
#395
b1 "
b1 -
b1 6
b1 <
b1 =
b1 >
1'
#400
0'
#405
03
11
b0 "
b0 -
b0 6
b0 <
b0 =
b0 >
1'
#410
0'
#415
b1 $
b1 +
b1 5
b1 9
b1 ?
b1 @
13
01
b1001 "
b1001 -
b1001 6
b1001 <
b1001 =
b1001 >
1'
#420
0'
#425
b1000 "
b1000 -
b1000 6
b1000 <
b1000 =
b1000 >
1'
#430
0'
#435
b111 "
b111 -
b111 6
b111 <
b111 =
b111 >
1'
#440
0'
#445
b110 "
b110 -
b110 6
b110 <
b110 =
b110 >
1'
#450
0'
#455
b101 "
b101 -
b101 6
b101 <
b101 =
b101 >
1'
#460
0'
#465
b100 "
b100 -
b100 6
b100 <
b100 =
b100 >
1'
#470
0'
#475
b11 "
b11 -
b11 6
b11 <
b11 =
b11 >
1'
#480
0'
#485
b10 "
b10 -
b10 6
b10 <
b10 =
b10 >
1'
#490
0'
#495
b1 "
b1 -
b1 6
b1 <
b1 =
b1 >
1'
#500
0'
#505
03
11
b0 "
b0 -
b0 6
b0 <
b0 =
b0 >
1'
#510
0'
#515
02
1/
b0 $
b0 +
b0 5
b0 9
b0 ?
b0 @
13
01
b1001 "
b1001 -
b1001 6
b1001 <
b1001 =
b1001 >
1'
#520
0'
#525
b1000 "
b1000 -
b1000 6
b1000 <
b1000 =
b1000 >
b1000 #
b1000 ,
b1000 7
b1000 8
b1000 :
1'
#530
0'
#535
b111 #
b111 ,
b111 7
b111 8
b111 :
b111 "
b111 -
b111 6
b111 <
b111 =
b111 >
1'
#540
0'
#545
b110 "
b110 -
b110 6
b110 <
b110 =
b110 >
b110 #
b110 ,
b110 7
b110 8
b110 :
1'
#550
0'
#555
b101 #
b101 ,
b101 7
b101 8
b101 :
b101 "
b101 -
b101 6
b101 <
b101 =
b101 >
1'
#560
0'
#565
b100 "
b100 -
b100 6
b100 <
b100 =
b100 >
b100 #
b100 ,
b100 7
b100 8
b100 :
1'
#570
0'
#575
b11 #
b11 ,
b11 7
b11 8
b11 :
b11 "
b11 -
b11 6
b11 <
b11 =
b11 >
1'
#580
0'
#585
b10 "
b10 -
b10 6
b10 <
b10 =
b10 >
b10 #
b10 ,
b10 7
b10 8
b10 :
1'
#590
0'
#595
b1 #
b1 ,
b1 7
b1 8
b1 :
b1 "
b1 -
b1 6
b1 <
b1 =
b1 >
1'
#600
0'
#605
x!
03
11
b0 "
b0 -
b0 6
b0 <
b0 =
b0 >
04
10
b0 #
b0 ,
b0 7
b0 8
b0 :
1'
#610
0'
#615
0!
14
00
b1001 #
b1001 ,
b1001 7
b1001 8
b1001 :
12
0/
b101 $
b101 +
b101 5
b101 9
b101 ?
b101 @
13
01
b1001 "
b1001 -
b1001 6
b1001 <
b1001 =
b1001 >
1'
#620
0'
#625
b1000 "
b1000 -
b1000 6
b1000 <
b1000 =
b1000 >
1'
#630
0'
#635
b111 "
b111 -
b111 6
b111 <
b111 =
b111 >
1'
#640
0'
#645
b110 "
b110 -
b110 6
b110 <
b110 =
b110 >
1'
#650
0'
#655
b101 "
b101 -
b101 6
b101 <
b101 =
b101 >
1'
#660
0'
#665
b100 "
b100 -
b100 6
b100 <
b100 =
b100 >
1'
#670
0'
#675
b11 "
b11 -
b11 6
b11 <
b11 =
b11 >
1'
#680
0'
#685
b10 "
b10 -
b10 6
b10 <
b10 =
b10 >
1'
#690
0'
#695
b1 "
b1 -
b1 6
b1 <
b1 =
b1 >
1'
#700
0'
#705
03
11
b0 "
b0 -
b0 6
b0 <
b0 =
b0 >
1'
#710
0'
#715
b100 $
b100 +
b100 5
b100 9
b100 ?
b100 @
13
01
b1001 "
b1001 -
b1001 6
b1001 <
b1001 =
b1001 >
1'
#720
0'
#725
b1000 "
b1000 -
b1000 6
b1000 <
b1000 =
b1000 >
1'
#730
0'
#735
b111 "
b111 -
b111 6
b111 <
b111 =
b111 >
1'
#740
0'
#745
b110 "
b110 -
b110 6
b110 <
b110 =
b110 >
1'
#750
0'
#755
b101 "
b101 -
b101 6
b101 <
b101 =
b101 >
1'
#760
0'
#765
b100 "
b100 -
b100 6
b100 <
b100 =
b100 >
1'
#770
0'
#775
b11 "
b11 -
b11 6
b11 <
b11 =
b11 >
1'
#780
0'
#785
b10 "
b10 -
b10 6
b10 <
b10 =
b10 >
1'
#790
0'
#795
b1 "
b1 -
b1 6
b1 <
b1 =
b1 >
1'
#800
0'
#805
03
11
b0 "
b0 -
b0 6
b0 <
b0 =
b0 >
1'
#810
0'
#815
b11 $
b11 +
b11 5
b11 9
b11 ?
b11 @
13
01
b1001 "
b1001 -
b1001 6
b1001 <
b1001 =
b1001 >
1'
#820
0'
#825
b1000 "
b1000 -
b1000 6
b1000 <
b1000 =
b1000 >
1'
#830
0'
#835
b111 "
b111 -
b111 6
b111 <
b111 =
b111 >
1'
#840
0'
#845
b110 "
b110 -
b110 6
b110 <
b110 =
b110 >
1'
#850
0'
#855
b101 "
b101 -
b101 6
b101 <
b101 =
b101 >
1'
#860
0'
#865
b100 "
b100 -
b100 6
b100 <
b100 =
b100 >
1'
#870
0'
#875
b11 "
b11 -
b11 6
b11 <
b11 =
b11 >
1'
#880
0'
#885
b10 "
b10 -
b10 6
b10 <
b10 =
b10 >
1'
#890
0'
#895
b1 "
b1 -
b1 6
b1 <
b1 =
b1 >
1'
#900
0'
#905
03
11
b0 "
b0 -
b0 6
b0 <
b0 =
b0 >
1'
#910
0'
#915
b10 $
b10 +
b10 5
b10 9
b10 ?
b10 @
13
01
b1001 "
b1001 -
b1001 6
b1001 <
b1001 =
b1001 >
1'
#920
0'
#925
b1000 "
b1000 -
b1000 6
b1000 <
b1000 =
b1000 >
1'
#930
0'
#935
b111 "
b111 -
b111 6
b111 <
b111 =
b111 >
1'
#940
0'
#945
b110 "
b110 -
b110 6
b110 <
b110 =
b110 >
1'
#950
0'
#955
b101 "
b101 -
b101 6
b101 <
b101 =
b101 >
1'
#960
0'
#965
b100 "
b100 -
b100 6
b100 <
b100 =
b100 >
1'
#970
0'
#975
b11 "
b11 -
b11 6
b11 <
b11 =
b11 >
1'
#980
0'
#985
b10 "
b10 -
b10 6
b10 <
b10 =
b10 >
1'
#990
0'
#995
b1 "
b1 -
b1 6
b1 <
b1 =
b1 >
1'
#1000
0'
#1005
03
11
b0 "
b0 -
b0 6
b0 <
b0 =
b0 >
1'
#1010
0'
#1015
b1 $
b1 +
b1 5
b1 9
b1 ?
b1 @
13
01
b1001 "
b1001 -
b1001 6
b1001 <
b1001 =
b1001 >
1'
#1020
0'
#1025
b1000 "
b1000 -
b1000 6
b1000 <
b1000 =
b1000 >
1'
#1030
0'
#1035
b111 "
b111 -
b111 6
b111 <
b111 =
b111 >
1'
#1040
0'
#1045
b110 "
b110 -
b110 6
b110 <
b110 =
b110 >
1'
#1050
0'
#1055
b101 "
b101 -
b101 6
b101 <
b101 =
b101 >
1'
#1060
0'
#1065
b100 "
b100 -
b100 6
b100 <
b100 =
b100 >
1'
#1070
0'
#1075
b11 "
b11 -
b11 6
b11 <
b11 =
b11 >
1'
#1080
0'
#1085
b10 "
b10 -
b10 6
b10 <
b10 =
b10 >
1'
#1090
0'
#1095
b1 "
b1 -
b1 6
b1 <
b1 =
b1 >
1'
#1100
0'
#1105
03
11
b0 "
b0 -
b0 6
b0 <
b0 =
b0 >
1'
#1110
0'
#1115
02
1/
b0 $
b0 +
b0 5
b0 9
b0 ?
b0 @
13
01
b1001 "
b1001 -
b1001 6
b1001 <
b1001 =
b1001 >
1'
#1120
0'
#1125
b1000 "
b1000 -
b1000 6
b1000 <
b1000 =
b1000 >
b1000 #
b1000 ,
b1000 7
b1000 8
b1000 :
1'
#1130
0'
#1135
b111 #
b111 ,
b111 7
b111 8
b111 :
b111 "
b111 -
b111 6
b111 <
b111 =
b111 >
1'
#1140
0'
#1145
b110 "
b110 -
b110 6
b110 <
b110 =
b110 >
b110 #
b110 ,
b110 7
b110 8
b110 :
1'
#1150
0'
#1155
b101 #
b101 ,
b101 7
b101 8
b101 :
b101 "
b101 -
b101 6
b101 <
b101 =
b101 >
1'
#1160
0'
#1165
b100 "
b100 -
b100 6
b100 <
b100 =
b100 >
b100 #
b100 ,
b100 7
b100 8
b100 :
1'
#1170
0'
#1175
b11 #
b11 ,
b11 7
b11 8
b11 :
b11 "
b11 -
b11 6
b11 <
b11 =
b11 >
1'
#1180
0'
#1185
b10 "
b10 -
b10 6
b10 <
b10 =
b10 >
b10 #
b10 ,
b10 7
b10 8
b10 :
1'
#1190
0'
#1195
b1 #
b1 ,
b1 7
b1 8
b1 :
b1 "
b1 -
b1 6
b1 <
b1 =
b1 >
1'
#1200
0'
#1205
x!
03
11
b0 "
b0 -
b0 6
b0 <
b0 =
b0 >
04
10
b0 #
b0 ,
b0 7
b0 8
b0 :
1'
#1210
0'
#1215
0!
14
00
b1001 #
b1001 ,
b1001 7
b1001 8
b1001 :
12
0/
b101 $
b101 +
b101 5
b101 9
b101 ?
b101 @
13
01
b1001 "
b1001 -
b1001 6
b1001 <
b1001 =
b1001 >
1'
#1220
0'
#1225
b1000 "
b1000 -
b1000 6
b1000 <
b1000 =
b1000 >
1'
#1230
0'
#1235
b111 "
b111 -
b111 6
b111 <
b111 =
b111 >
1'
#1240
0'
#1245
b110 "
b110 -
b110 6
b110 <
b110 =
b110 >
1'
#1250
0'
#1255
b101 "
b101 -
b101 6
b101 <
b101 =
b101 >
1'
#1260
0'
#1265
b100 "
b100 -
b100 6
b100 <
b100 =
b100 >
1'
#1270
0'
#1275
b11 "
b11 -
b11 6
b11 <
b11 =
b11 >
1'
#1280
0'
#1285
b10 "
b10 -
b10 6
b10 <
b10 =
b10 >
1'
#1290
0'
#1295
b1 "
b1 -
b1 6
b1 <
b1 =
b1 >
1'
#1300
0'
#1305
03
11
b0 "
b0 -
b0 6
b0 <
b0 =
b0 >
1'
#1310
0'
#1315
b100 $
b100 +
b100 5
b100 9
b100 ?
b100 @
13
01
b1001 "
b1001 -
b1001 6
b1001 <
b1001 =
b1001 >
1'
#1320
0'
#1325
b1000 "
b1000 -
b1000 6
b1000 <
b1000 =
b1000 >
1'
#1330
0'
#1335
b111 "
b111 -
b111 6
b111 <
b111 =
b111 >
1'
#1340
0'
#1345
b110 "
b110 -
b110 6
b110 <
b110 =
b110 >
1'
#1350
0'
#1355
b101 "
b101 -
b101 6
b101 <
b101 =
b101 >
1'
#1360
0'
#1365
b100 "
b100 -
b100 6
b100 <
b100 =
b100 >
1'
#1370
0'
#1375
b11 "
b11 -
b11 6
b11 <
b11 =
b11 >
1'
#1380
0'
#1385
b10 "
b10 -
b10 6
b10 <
b10 =
b10 >
1'
#1390
0'
#1395
b1 "
b1 -
b1 6
b1 <
b1 =
b1 >
1'
#1400
0'
#1405
03
11
b0 "
b0 -
b0 6
b0 <
b0 =
b0 >
1'
#1410
0'
#1415
b11 $
b11 +
b11 5
b11 9
b11 ?
b11 @
13
01
b1001 "
b1001 -
b1001 6
b1001 <
b1001 =
b1001 >
1'
#1420
0'
#1425
b1000 "
b1000 -
b1000 6
b1000 <
b1000 =
b1000 >
1'
#1430
0'
#1435
b111 "
b111 -
b111 6
b111 <
b111 =
b111 >
1'
#1440
0'
#1445
b110 "
b110 -
b110 6
b110 <
b110 =
b110 >
1'
#1450
0'
#1455
b101 "
b101 -
b101 6
b101 <
b101 =
b101 >
1'
#1460
0'
#1465
b100 "
b100 -
b100 6
b100 <
b100 =
b100 >
1'
#1470
0'
#1475
b11 "
b11 -
b11 6
b11 <
b11 =
b11 >
1'
#1480
0'
#1485
b10 "
b10 -
b10 6
b10 <
b10 =
b10 >
1'
#1490
0'
#1495
b1 "
b1 -
b1 6
b1 <
b1 =
b1 >
1'
#1500
0'
#1505
03
11
b0 "
b0 -
b0 6
b0 <
b0 =
b0 >
1'
#1510
0'
#1515
b10 $
b10 +
b10 5
b10 9
b10 ?
b10 @
13
01
b1001 "
b1001 -
b1001 6
b1001 <
b1001 =
b1001 >
1'
#1520
0'
#1525
b1000 "
b1000 -
b1000 6
b1000 <
b1000 =
b1000 >
1'
#1530
0'
#1535
b111 "
b111 -
b111 6
b111 <
b111 =
b111 >
1'
#1540
0'
#1545
b110 "
b110 -
b110 6
b110 <
b110 =
b110 >
1'
#1550
0'
#1555
b101 "
b101 -
b101 6
b101 <
b101 =
b101 >
1'
#1560
0'
#1565
b100 "
b100 -
b100 6
b100 <
b100 =
b100 >
1'
#1570
0'
#1575
b11 "
b11 -
b11 6
b11 <
b11 =
b11 >
1'
#1580
0'
#1585
b10 "
b10 -
b10 6
b10 <
b10 =
b10 >
1'
#1590
0'
#1595
b1 "
b1 -
b1 6
b1 <
b1 =
b1 >
1'
#1600
0'
#1605
03
11
b0 "
b0 -
b0 6
b0 <
b0 =
b0 >
1'
#1610
0'
#1615
b1 $
b1 +
b1 5
b1 9
b1 ?
b1 @
13
01
b1001 "
b1001 -
b1001 6
b1001 <
b1001 =
b1001 >
1'
#1620
0'
#1625
b1000 "
b1000 -
b1000 6
b1000 <
b1000 =
b1000 >
1'
#1630
0'
#1635
b111 "
b111 -
b111 6
b111 <
b111 =
b111 >
1'
#1640
0'
#1645
b110 "
b110 -
b110 6
b110 <
b110 =
b110 >
1'
#1650
0'
#1655
b101 "
b101 -
b101 6
b101 <
b101 =
b101 >
1'
#1660
0'
#1665
b100 "
b100 -
b100 6
b100 <
b100 =
b100 >
1'
#1670
0'
#1675
b11 "
b11 -
b11 6
b11 <
b11 =
b11 >
1'
#1680
0'
#1685
b10 "
b10 -
b10 6
b10 <
b10 =
b10 >
1'
#1690
0'
#1695
b1 "
b1 -
b1 6
b1 <
b1 =
b1 >
1'
#1700
0'
#1705
03
11
b0 "
b0 -
b0 6
b0 <
b0 =
b0 >
1'
#1710
0'
#1715
02
1/
b0 $
b0 +
b0 5
b0 9
b0 ?
b0 @
13
01
b1001 "
b1001 -
b1001 6
b1001 <
b1001 =
b1001 >
1'
#1720
0'
#1725
b1000 "
b1000 -
b1000 6
b1000 <
b1000 =
b1000 >
b1000 #
b1000 ,
b1000 7
b1000 8
b1000 :
1'
#1730
0'
#1735
b111 #
b111 ,
b111 7
b111 8
b111 :
b111 "
b111 -
b111 6
b111 <
b111 =
b111 >
1'
#1740
0'
#1745
b110 "
b110 -
b110 6
b110 <
b110 =
b110 >
b110 #
b110 ,
b110 7
b110 8
b110 :
1'
#1750
0'
#1755
b101 #
b101 ,
b101 7
b101 8
b101 :
b101 "
b101 -
b101 6
b101 <
b101 =
b101 >
1'
#1760
0'
#1765
b100 "
b100 -
b100 6
b100 <
b100 =
b100 >
b100 #
b100 ,
b100 7
b100 8
b100 :
1'
#1770
0'
#1775
b11 #
b11 ,
b11 7
b11 8
b11 :
b11 "
b11 -
b11 6
b11 <
b11 =
b11 >
1'
#1780
0'
#1785
b10 "
b10 -
b10 6
b10 <
b10 =
b10 >
b10 #
b10 ,
b10 7
b10 8
b10 :
1'
#1790
0'
#1795
b1 #
b1 ,
b1 7
b1 8
b1 :
b1 "
b1 -
b1 6
b1 <
b1 =
b1 >
1'
#1800
0'
#1805
x!
03
11
b0 "
b0 -
b0 6
b0 <
b0 =
b0 >
04
10
b0 #
b0 ,
b0 7
b0 8
b0 :
1'
#1810
0'
#1815
0!
14
00
b1001 #
b1001 ,
b1001 7
b1001 8
b1001 :
12
0/
b101 $
b101 +
b101 5
b101 9
b101 ?
b101 @
13
01
b1001 "
b1001 -
b1001 6
b1001 <
b1001 =
b1001 >
1'
#1820
0'
#1825
b1000 "
b1000 -
b1000 6
b1000 <
b1000 =
b1000 >
1'
#1830
0'
#1835
b111 "
b111 -
b111 6
b111 <
b111 =
b111 >
1'
#1840
0'
#1845
b110 "
b110 -
b110 6
b110 <
b110 =
b110 >
1'
#1850
0'
#1855
b101 "
b101 -
b101 6
b101 <
b101 =
b101 >
1'
#1860
0'
#1865
b100 "
b100 -
b100 6
b100 <
b100 =
b100 >
1'
#1870
0'
#1875
b11 "
b11 -
b11 6
b11 <
b11 =
b11 >
1'
#1880
0'
#1885
b10 "
b10 -
b10 6
b10 <
b10 =
b10 >
1'
#1890
0'
#1895
b1 "
b1 -
b1 6
b1 <
b1 =
b1 >
1'
#1900
0'
#1905
03
11
b0 "
b0 -
b0 6
b0 <
b0 =
b0 >
1'
#1910
0'
#1915
b100 $
b100 +
b100 5
b100 9
b100 ?
b100 @
13
01
b1001 "
b1001 -
b1001 6
b1001 <
b1001 =
b1001 >
1'
#1920
0'
#1925
b1000 "
b1000 -
b1000 6
b1000 <
b1000 =
b1000 >
1'
#1930
0'
#1935
b111 "
b111 -
b111 6
b111 <
b111 =
b111 >
1'
#1940
0'
#1945
b110 "
b110 -
b110 6
b110 <
b110 =
b110 >
1'
#1950
0'
#1955
b101 "
b101 -
b101 6
b101 <
b101 =
b101 >
1'
#1960
0'
#1965
b100 "
b100 -
b100 6
b100 <
b100 =
b100 >
1'
#1970
0'
#1975
b11 "
b11 -
b11 6
b11 <
b11 =
b11 >
1'
#1980
0'
#1985
b10 "
b10 -
b10 6
b10 <
b10 =
b10 >
1'
#1990
0'
#1995
b1 "
b1 -
b1 6
b1 <
b1 =
b1 >
1'
#2000
0'
#2005
03
11
b0 "
b0 -
b0 6
b0 <
b0 =
b0 >
1'
#2010
0'
#2015
b11 $
b11 +
b11 5
b11 9
b11 ?
b11 @
13
01
b1001 "
b1001 -
b1001 6
b1001 <
b1001 =
b1001 >
1'
#2020
0'
#2025
b1000 "
b1000 -
b1000 6
b1000 <
b1000 =
b1000 >
1'
#2030
0'
#2035
b111 "
b111 -
b111 6
b111 <
b111 =
b111 >
1'
#2040
0'
#2045
b110 "
b110 -
b110 6
b110 <
b110 =
b110 >
1'
#2050
0'
#2055
b101 "
b101 -
b101 6
b101 <
b101 =
b101 >
1'
#2060
0'
#2065
b100 "
b100 -
b100 6
b100 <
b100 =
b100 >
1'
#2070
0'
#2075
b11 "
b11 -
b11 6
b11 <
b11 =
b11 >
1'
#2080
0'
#2085
b10 "
b10 -
b10 6
b10 <
b10 =
b10 >
1'
#2090
0'
#2095
b1 "
b1 -
b1 6
b1 <
b1 =
b1 >
1'
#2100
0'
#2105
03
11
b0 "
b0 -
b0 6
b0 <
b0 =
b0 >
1'
#2110
0'
#2115
b10 $
b10 +
b10 5
b10 9
b10 ?
b10 @
13
01
b1001 "
b1001 -
b1001 6
b1001 <
b1001 =
b1001 >
1'
#2120
0'
