SD-Projeto3/SD-Projeto3/nivel1/nivel2/contador/nivel3/contador_mod10/contador_mod10.v
module contador_mod10 (data, clk, load, en, clearn, count, tc, count_end);
  // 1) Adicionei o input count_end, ele vai servir para parar a contagem
  // regressiva quando os algarismos dos min, dez_seg e seg forem
  // iguais a 0, e não simplesmente fazer um loop infinito.
  // 2) Troquei count_end para ser um output, que vai indicar quando chegou a zero
  input wire [3:0] data;
  input wire clk, load, en, clearn;
  output reg [3:0] count;
  output wire tc; 
  output wire count_end;

  always @ (negedge clearn) // Lembrar de trocar o reset e o stop (feito)
  begin
    count = 4'b0000;
  end

  assign count_end = (count == 4'b0000) ? 1'b1 : 1'b0;
  assign tc = en & count_end;

  always @ (posedge clk)
  begin
    if (en) 
      case (count)
        4'b1001: begin
          count <= 4'b1000;
        end // 9 -> 8
        4'b0001: begin 
          count <= 4'b0000;
        end  // 1 -> 0
        4'b0000: begin
          count <= 4'b1001;
        end // 0 -> 9
        default: count <= count - 4'b0001;
      endcase

    else begin


      if(!load) // Lembrar q aq o valor do load tá invertido
        count <= data;
    end
  end
endmodule

SD-Projeto3/SD-Projeto3/nivel1/nivel2/contador/nivel3/contador_mod6/contador_mod6.v
module contador_mod6(data, clk, load, en, clearn, count, tc, count_end);
  // 1) Por algum motivo, basicamente todos as variáveis que são de 
  // 4-bits agora, estavam como variáveis de 3-bits, como isso tava
  // dando problema toda vez que dava run eu mudei tudo que era 
  // de 3-bits para 4-bits, sem alterar o funcionamento do módulo
  // (também mudei um pouco a testbench do contador_nivel2
  // por causa disso)
  // 2) Adicionei o input count_end, ele vai servir para parar a contagem
  // regressiva quando os algarismos dos min, dez_seg e seg forem
  // iguais a 0, e não simplesmente fazer um loop infinito.
  // 3) Troquei count_end para ser um output, que vai indicar 
  // quando chegou a zero.
  input wire [3:0] data;
  input wire clk, load, en, clearn;
  output reg [3:0] count;
  output wire tc;
  output wire count_end;

  always @ (negedge clearn) // lembrar de trocar o reset e o stop (feito)
  begin
    count = 4'b0000;
  end

  assign count_end = (count == 4'b0000) ? 1'b1 : 1'b0;
  assign tc = en & count_end;

  always @ (posedge clk)
  begin
    if (en) 
      case (count)
        4'b0101: begin
          count <= 4'b0100;
        end // 5 -> 4
        4'b0001: begin 
          count <= 4'b0000;
        end  // 1 -> 0
        4'b0000: begin
          count <= 4'b0101;
        end // 0 -> 5
        default: count <= count - 4'b0001;
      endcase

    else begin

      if(!load) // Lembrar q aq o valor do load tá invertido
        count <= data;
    end
  end
endmodule

SD-Projeto3/SD-Projeto3/nivel1/nivel2/contador/contador_nivel2.v
`include "nivel2/contador/nivel3/contador_mod10/contador_mod10.v"
`include "nivel2/contador/nivel3/contador_mod6/contador_mod6.v"
// (Mudar o endereço dos arquivos se for fazer teste local)
`timescale 1ns/1ps

module contador_nivel2(data, clk, enable, load, clear, count_us, count_ds, count_m, zero);

  input [3:0] data;
  input wire clk, enable, load, clear; // Lembrar q aq tudo menos o clk tá invertido (load equivale a loadn...)
  output wire [3:0] count_us, count_ds, count_m;
  output wire zero;
  
  wire tc1;
  wire tc2;
  wire tc3;
  wire zero1;
  wire zero2;
  wire zero3;

  // Quando a contagem chegar em 0, o controle do magnetron vai
  // ordenar a parada dele, e esse output do controle do magnetron
  // Vai ser também o enable desse contador, logo, o enable = 0 e
  // o contador irá parar automaticamente.

  // v Problema no nome dos módulos referenciados (consertado)
  contador_mod10 us(data, clk, load, enable, clear, count_us, tc1, zero1);
  contador_mod6 ds(count_us, clk, load, tc1, clear, count_ds, tc2, zero2);
  
  // v Problema no nome do módulo referenciado (consertado)
  contador_mod10 ms(count_ds, clk, load, tc2, clear, count_m, tc3, zero3);

  assign zero = zero1 & zero2 & zero3;
endmodule

SD-Projeto3/SD-Projeto3/nivel1/nivel2/contador/contador_nivel2_teste.v
`timescale 1ns/1ps
`include "contador_nivel2.v"

module contador_nivel2_teste();
    wire[3:0] minutes_tb, tens_secs_tb, secs_tb;
    wire timer_done_tb;
    reg [3:0]  data_tb;
    reg clearn_tb, enable_tb, loadn_tb, CLK_tb;

    contador_nivel2 DUT(data_tb, CLK_tb, enable_tb, loadn_tb, clearn_tb,
                  secs_tb, tens_secs_tb, minutes_tb, timer_done_tb);

    initial begin
        $dumpfile("contador_nivel2_teste.vcd");
        $dumpvars(0,contador_nivel2_teste);
        CLK_tb  = 1'b0;
        enable_tb = 1'b0; 
        loadn_tb  = 1'b0;
    end

    always begin
        #1 CLK_tb = loadn_tb? ~CLK_tb : CLK_tb;
    end

    initial begin    

        clearn_tb = 1'b1; #0.5
        clearn_tb = 1'b0; #0.5
        clearn_tb = 1'b1; #0.5

        data_tb =  2;   #0.04;
        CLK_tb = 1'b1;   #0.01;
        CLK_tb = 1'b0;   #0.95;

        data_tb =  1;   #0.04;
        CLK_tb = 1'b1;   #0.01;
        CLK_tb = 1'b0;   #0.95;

        data_tb =  7;   #0.04;
        CLK_tb = 1'b1;   #0.01;
        CLK_tb = 1'b0;   #0.95;

        data_tb =  9;   #0.04;
        CLK_tb = 1'b1;   #0.01;
        CLK_tb = 1'b0;   #0.95;

        enable_tb = 1; loadn_tb = 1; #1000;

        $finish();
    end
endmodule

SD-Projeto3/SD-Projeto3/nivel1/nivel2/contador/contador_nivel2_teste.vcd
$date
	Fri Oct 21 17:34:40 2022
$end
$version
	Icarus Verilog
$end
$timescale
	1ps
$end
$scope module contador_nivel2_teste $end
$var wire 4 ! minutes_tb [3:0] $end
$var wire 4 " secs_tb [3:0] $end
$var wire 4 # tens_secs_tb [3:0] $end
$var wire 1 $ timer_done_tb $end
$var reg 1 % CLK_tb $end
$var reg 1 & clearn_tb $end
$var reg 4 ' data_tb [3:0] $end
$var reg 1 ( enable_tb $end
$var reg 1 ) loadn_tb $end
$scope module DUT $end
$var wire 1 * clear $end
$var wire 1 + clk $end
$var wire 4 , count_ds [3:0] $end
$var wire 4 - count_m [3:0] $end
$var wire 4 . count_us [3:0] $end
$var wire 4 / data [3:0] $end
$var wire 1 0 enable $end
$var wire 1 1 load $end
$var wire 1 2 tc1 $end
$var wire 1 3 tc2 $end
$var wire 1 4 tc3 $end
$var wire 1 $ zero $end
$var wire 1 5 zero1 $end
$var wire 1 6 zero2 $end
$var wire 1 7 zero3 $end
$scope module us $end
$var wire 1 * clearn $end
$var wire 1 + clk $end
$var wire 1 5 count_end $end
$var wire 4 8 data [3:0] $end
$var wire 1 0 en $end
$var wire 1 1 load $end
$var wire 1 2 tc $end
$var reg 4 9 count [3:0] $end
$upscope $end
$scope module ds $end
$var wire 1 * clearn $end
$var wire 1 + clk $end
$var wire 1 6 count_end $end
$var wire 4 : data [3:0] $end
$var wire 1 2 en $end
$var wire 1 1 load $end
$var wire 1 3 tc $end
$var reg 4 ; count [3:0] $end
$upscope $end
$scope module ms $end
$var wire 1 * clearn $end
$var wire 1 + clk $end
$var wire 1 7 count_end $end
$var wire 4 < data [3:0] $end
$var wire 1 3 en $end
$var wire 1 1 load $end
$var wire 1 4 tc $end
$var reg 4 = count [3:0] $end
$upscope $end
$upscope $end
$upscope $end
$enddefinitions $end
#0
$dumpvars
bx =
bx <
bx ;
bx :
bx 9
bx 8
x7
x6
x5
04
03
02
01
00
bx /
bx .
bx -
bx ,
0+
1*
0)
0(
bx '
1&
0%
x$
bx #
bx "
bx !
$end
#500
1$
15
16
17
b0 9
b0 "
b0 .
b0 :
b0 ;
b0 #
b0 ,
b0 <
b0 =
b0 !
b0 -
0&
0*
#1000
1&
1*
#1500
b10 '
b10 /
b10 8
#1540
0$
05
b10 9
b10 "
b10 .
b10 :
1%
1+
#1550
0%
0+
#2500
b1 '
b1 /
b1 8
#2540
06
b10 ;
b10 #
b10 ,
b10 <
b1 9
b1 "
b1 .
b1 :
1%
1+
#2550
0%
0+
#3500
b111 '
b111 /
b111 8
#3540
07
b111 9
b111 "
b111 .
b111 :
b1 ;
b1 #
b1 ,
b1 <
b10 =
b10 !
b10 -
1%
1+
#3550
0%
0+
#4500
b1001 '
b1001 /
b1001 8
#4540
b1 =
b1 !
b1 -
b111 ;
b111 #
b111 ,
b111 <
b1001 9
b1001 "
b1001 .
b1001 :
1%
1+
#4550
0%
0+
#5500
1)
11
1(
10
#6000
b1000 9
b1000 "
b1000 .
b1000 :
1%
1+
#7000
0%
0+
#8000
b111 9
b111 "
b111 .
b111 :
1%
1+
#9000
0%
0+
#10000
b110 9
b110 "
b110 .
b110 :
1%
1+
#11000
0%
0+
#12000
b101 9
b101 "
b101 .
b101 :
1%
1+
#13000
0%
0+
#14000
b100 9
b100 "
b100 .
b100 :
1%
1+
#15000
0%
0+
#16000
b11 9
b11 "
b11 .
b11 :
1%
1+
#17000
0%
0+
#18000
b10 9
b10 "
b10 .
b10 :
1%
1+
#19000
0%
0+
#20000
b1 9
b1 "
b1 .
b1 :
1%
1+
#21000
0%
0+
#22000
12
15
b0 9
b0 "
b0 .
b0 :
1%
1+
#23000
0%
0+
#24000
02
05
b110 ;
b110 #
b110 ,
b110 <
b1001 9
b1001 "
b1001 .
b1001 :
1%
1+
#25000
0%
0+
#26000
b1000 9
b1000 "
b1000 .
b1000 :
1%
1+
#27000
0%
0+
#28000
b111 9
b111 "
b111 .
b111 :
1%
1+
#29000
0%
0+
#30000
b110 9
b110 "
b110 .
b110 :
1%
1+
#31000
0%
0+
#32000
b101 9
b101 "
b101 .
b101 :
1%
1+
#33000
0%
0+
#34000
b100 9
b100 "
b100 .
b100 :
1%
1+
#35000
0%
0+
#36000
b11 9
b11 "
b11 .
b11 :
1%
1+
#37000
0%
0+
#38000
b10 9
b10 "
b10 .
b10 :
1%
1+
#39000
0%
0+
#40000
b1 9
b1 "
b1 .
b1 :
1%
1+
#41000
0%
0+
#42000
12
15
b0 9
b0 "
b0 .
b0 :
1%
1+
#43000
0%
0+
#44000
02
05
b101 ;
b101 #
b101 ,
b101 <
b1001 9
b1001 "
b1001 .
b1001 :
1%
1+
#45000
0%
0+
#46000
b1000 9
b1000 "
b1000 .
b1000 :
1%
1+
#47000
0%
0+
#48000
b111 9
b111 "
b111 .
b111 :
1%
1+
#49000
0%
0+
#50000
b110 9
b110 "
b110 .
b110 :
1%
1+
#51000
0%
0+
#52000
b101 9
b101 "
b101 .
b101 :
1%
1+
#53000
0%
0+
#54000
b100 9
b100 "
b100 .
b100 :
1%
1+
#55000
0%
0+
#56000
b11 9
b11 "
b11 .
b11 :
1%
1+
#57000
0%
0+
#58000
b10 9
b10 "
b10 .
b10 :
1%
1+
#59000
0%
0+
#60000
b1 9
b1 "
b1 .
b1 :
1%
1+
#61000
0%
0+
#62000
12
15
b0 9
b0 "
b0 .
b0 :
1%
1+
#63000
0%
0+
#64000
02
05
b100 ;
b100 #
b100 ,
b100 <
b1001 9
b1001 "
b1001 .
b1001 :
1%
1+
#65000
0%
0+
#66000
b1000 9
b1000 "
b1000 .
b1000 :
1%
1+
#67000
0%
0+
#68000
b111 9
b111 "
b111 .
b111 :
1%
1+
#69000
0%
0+
#70000
b110 9
b110 "
b110 .
b110 :
1%
1+
#71000
0%
0+
#72000
b101 9
b101 "
b101 .
b101 :
1%
1+
#73000
0%
0+
#74000
b100 9
b100 "
b100 .
b100 :
1%
1+
#75000
0%
0+
#76000
b11 9
b11 "
b11 .
b11 :
1%
1+
#77000
0%
0+
#78000
b10 9
b10 "
b10 .
b10 :
1%
1+
#79000
0%
0+
#80000
b1 9
b1 "
b1 .
b1 :
1%
1+
#81000
0%
0+
#82000
12
15
b0 9
b0 "
b0 .
b0 :
1%
1+
#83000
0%
0+
#84000
02
05
b11 ;
b11 #
b11 ,
b11 <
b1001 9
b1001 "
b1001 .
b1001 :
1%
1+
#85000
0%
0+
#86000
b1000 9
b1000 "
b1000 .
b1000 :
1%
1+
#87000
0%
0+
#88000
b111 9
b111 "
b111 .
b111 :
1%
1+
#89000
0%
0+
#90000
b110 9
b110 "
b110 .
b110 :
1%
1+
#91000
0%
0+
#92000
b101 9
b101 "
b101 .
b101 :
1%
1+
#93000
0%
0+
#94000
b100 9
b100 "
b100 .
b100 :
1%
1+
#95000
0%
0+
#96000
b11 9
b11 "
b11 .
b11 :
1%
1+
#97000
0%
0+
#98000
b10 9
b10 "
b10 .
b10 :
1%
1+
#99000
0%
0+
#100000
b1 9
b1 "
b1 .
b1 :
1%
1+
#101000
0%
0+
#102000
12
15
b0 9
b0 "
b0 .
b0 :
1%
1+
#103000
0%
0+
#104000
02
05
b10 ;
b10 #
b10 ,
b10 <
b1001 9
b1001 "
b1001 .
b1001 :
1%
1+
#105000
0%
0+
#106000
b1000 9
b1000 "
b1000 .
b1000 :
1%
1+
#107000
0%
0+
#108000
b111 9
b111 "
b111 .
b111 :
1%
1+
#109000
0%
0+
#110000
b110 9
b110 "
b110 .
b110 :
1%
1+
#111000
0%
0+
#112000
b101 9
b101 "
b101 .
b101 :
1%
1+
#113000
0%
0+
#114000
b100 9
b100 "
b100 .
b100 :
1%
1+
#115000
0%
0+
#116000
b11 9
b11 "
b11 .
b11 :
1%
1+
#117000
0%
0+
#118000
b10 9
b10 "
b10 .
b10 :
1%
1+
#119000
0%
0+
#120000
b1 9
b1 "
b1 .
b1 :
1%
1+
#121000
0%
0+
#122000
12
15
b0 9
b0 "
b0 .
b0 :
1%
1+
#123000
0%
0+
#124000
02
05
b1 ;
b1 #
b1 ,
b1 <
b1001 9
b1001 "
b1001 .
b1001 :
1%
1+
#125000
0%
0+
#126000
b1000 9
b1000 "
b1000 .
b1000 :
1%
1+
#127000
0%
0+
#128000
b111 9
b111 "
b111 .
b111 :
1%
1+
#129000
0%
0+
#130000
b110 9
b110 "
b110 .
b110 :
1%
1+
#131000
0%
0+
#132000
b101 9
b101 "
b101 .
b101 :
1%
1+
#133000
0%
0+
#134000
b100 9
b100 "
b100 .
b100 :
1%
1+
#135000
0%
0+
#136000
b11 9
b11 "
b11 .
b11 :
1%
1+
#137000
0%
0+
#138000
b10 9
b10 "
b10 .
b10 :
1%
1+
#139000
0%
0+
#140000
b1 9
b1 "
b1 .
b1 :
1%
1+
#141000
0%
0+
#142000
12
15
b0 9
b0 "
b0 .
b0 :
1%
1+
#143000
0%
0+
#144000
02
16
05
b0 ;
b0 #
b0 ,
b0 <
b1001 9
b1001 "
b1001 .
b1001 :
1%
1+
#145000
0%
0+
#146000
b1000 9
b1000 "
b1000 .
b1000 :
1%
1+
#147000
0%
0+
#148000
b111 9
b111 "
b111 .
b111 :
1%
1+
#149000
0%
0+
#150000
b110 9
b110 "
b110 .
b110 :
1%
1+
#151000
0%
0+
#152000
b101 9
b101 "
b101 .
b101 :
1%
1+
#153000
0%
0+
#154000
b100 9
b100 "
b100 .
b100 :
1%
1+
#155000
0%
0+
#156000
b11 9
b11 "
b11 .
b11 :
1%
1+
#157000
0%
0+
#158000
b10 9
b10 "
b10 .
b10 :
1%
1+
#159000
0%
0+
#160000
b1 9
b1 "
b1 .
b1 :
1%
1+
#161000
0%
0+
#162000
13
12
15
b0 9
b0 "
b0 .
b0 :
1%
1+
#163000
0%
0+
#164000
03
02
17
06
05
b0 =
b0 !
b0 -
b101 ;
b101 #
b101 ,
b101 <
b1001 9
b1001 "
b1001 .
b1001 :
1%
1+
#165000
0%
0+
#166000
b1000 9
b1000 "
b1000 .
b1000 :
1%
1+
#167000
0%
0+
#168000
b111 9
b111 "
b111 .
b111 :
1%
1+
#169000
0%
0+
#170000
b110 9
b110 "
b110 .
b110 :
1%
1+
#171000
0%
0+
#172000
b101 9
b101 "
b101 .
b101 :
1%
1+
#173000
0%
0+
#174000
b100 9
b100 "
b100 .
b100 :
1%
1+
#175000
0%
0+
#176000
b11 9
b11 "
b11 .
b11 :
1%
1+
#177000
0%
0+
#178000
b10 9
b10 "
b10 .
b10 :
1%
1+
#179000
0%
0+
#180000
b1 9
b1 "
b1 .
b1 :
1%
1+
#181000
0%
0+
#182000
12
15
b0 9
b0 "
b0 .
b0 :
1%
1+
#183000
0%
0+
#184000
02
05
b100 ;
b100 #
b100 ,
b100 <
b1001 9
b1001 "
b1001 .
b1001 :
1%
1+
#185000
0%
0+
#186000
b1000 9
b1000 "
b1000 .
b1000 :
1%
1+
#187000
0%
0+
#188000
b111 9
b111 "
b111 .
b111 :
1%
1+
#189000
0%
0+
#190000
b110 9
b110 "
b110 .
b110 :
1%
1+
#191000
0%
0+
#192000
b101 9
b101 "
b101 .
b101 :
1%
1+
#193000
0%
0+
#194000
b100 9
b100 "
b100 .
b100 :
1%
1+
#195000
0%
0+
#196000
b11 9
b11 "
b11 .
b11 :
1%
1+
#197000
0%
0+
#198000
b10 9
b10 "
b10 .
b10 :
1%
1+
#199000
0%
0+
#200000
b1 9
b1 "
b1 .
b1 :
1%
1+
#201000
0%
0+
#202000
12
15
b0 9
b0 "
b0 .
b0 :
1%
1+
#203000
0%
0+
#204000
02
05
b11 ;
b11 #
b11 ,
b11 <
b1001 9
b1001 "
b1001 .
b1001 :
1%
1+
#205000
0%
0+
#206000
b1000 9
b1000 "
b1000 .
b1000 :
1%
1+
#207000
0%
0+
#208000
b111 9
b111 "
b111 .
b111 :
1%
1+
#209000
0%
0+
#210000
b110 9
b110 "
b110 .
b110 :
1%
1+
#211000
0%
0+
#212000
b101 9
b101 "
b101 .
b101 :
1%
1+
#213000
0%
0+
#214000
b100 9
b100 "
b100 .
b100 :
1%
1+
#215000
0%
0+
#216000
b11 9
b11 "
b11 .
b11 :
1%
1+
#217000
0%
0+
#218000
b10 9
b10 "
b10 .
b10 :
1%
1+
#219000
0%
0+
#220000
b1 9
b1 "
b1 .
b1 :
1%
1+
#221000
0%
0+
#222000
12
15
b0 9
b0 "
b0 .
b0 :
1%
1+
#223000
0%
0+
#224000
02
05
b10 ;
b10 #
b10 ,
b10 <
b1001 9
b1001 "
b1001 .
b1001 :
1%
1+
#225000
0%
0+
#226000
b1000 9
b1000 "
b1000 .
b1000 :
1%
1+
#227000
0%
0+
#228000
b111 9
b111 "
b111 .
b111 :
1%
1+
#229000
0%
0+
#230000
b110 9
b110 "
b110 .
b110 :
1%
1+
#231000
0%
0+
#232000
b101 9
b101 "
b101 .
b101 :
1%
1+
#233000
0%
0+
#234000
b100 9
b100 "
b100 .
b100 :
1%
1+
#235000
0%
0+
#236000
b11 9
b11 "
b11 .
b11 :
1%
1+
#237000
0%
0+
#238000
b10 9
b10 "
b10 .
b10 :
1%
1+
#239000
0%
0+
#240000
b1 9
b1 "
b1 .
b1 :
1%
1+
#241000
0%
0+
#242000
12
15
b0 9
b0 "
b0 .
b0 :
1%
1+
#243000
0%
0+
#244000
02
05
b1 ;
b1 #
b1 ,
b1 <
b1001 9
b1001 "
b1001 .
b1001 :
1%
1+
#245000
0%
0+
#246000
b1000 9
b1000 "
b1000 .
b1000 :
1%
1+
#247000
0%
0+
#248000
b111 9
b111 "
b111 .
b111 :
1%
1+
#249000
0%
0+
#250000
b110 9
b110 "
b110 .
b110 :
1%
1+
#251000
0%
0+
#252000
b101 9
b101 "
b101 .
b101 :
1%
1+
#253000
0%
0+
#254000
b100 9
b100 "
b100 .
b100 :
1%
1+
#255000
0%
0+
#256000
b11 9
b11 "
b11 .
b11 :
1%
1+
#257000
0%
0+
#258000
b10 9
b10 "
b10 .
b10 :
1%
1+
#259000
0%
0+
#260000
b1 9
b1 "
b1 .
b1 :
1%
1+
#261000
0%
0+
#262000
12
15
b0 9
b0 "
b0 .
b0 :
1%
1+
#263000
0%
0+
#264000
02
16
05
b0 ;
b0 #
b0 ,
b0 <
b1001 9
b1001 "
b1001 .
b1001 :
1%
1+
#265000
0%
0+
#266000
b1000 9
b1000 "
b1000 .
b1000 :
1%
1+
#267000
0%
0+
#268000
b111 9
b111 "
b111 .
b111 :
1%
1+
#269000
0%
0+
#270000
b110 9
b110 "
b110 .
b110 :
1%
1+
#271000
0%
0+
#272000
b101 9
b101 "
b101 .
b101 :
1%
1+
#273000
0%
0+
#274000
b100 9
b100 "
b100 .
b100 :
1%
1+
#275000
0%
0+
#276000
b11 9
b11 "
b11 .
b11 :
1%
1+
#277000
0%
0+
#278000
b10 9
b10 "
b10 .
b10 :
1%
1+
#279000
0%
0+
#280000
b1 9
b1 "
b1 .
b1 :
1%
1+
#281000
0%
0+
#282000
14
13
1$
12
15
b0 9
b0 "
b0 .
b0 :
1%
1+
#283000
0%
0+
#284000
04
0$
03
02
07
06
05
b1001 =
b1001 !
b1001 -
b101 ;
b101 #
b101 ,
b101 <
b1001 9
b1001 "
b1001 .
b1001 :
1%
1+
#285000
0%
0+
#286000
b1000 9
b1000 "
b1000 .
b1000 :
1%
1+
#287000
0%
0+
#288000
b111 9
b111 "
b111 .
b111 :
1%
1+
#289000
0%
0+
#290000
b110 9
b110 "
b110 .
b110 :
1%
1+
#291000
0%
0+
#292000
b101 9
b101 "
b101 .
b101 :
1%
1+
#293000
0%
0+
#294000
b100 9
b100 "
b100 .
b100 :
1%
1+
#295000
0%
0+
#296000
b11 9
b11 "
b11 .
b11 :
1%
1+
#297000
0%
0+
#298000
b10 9
b10 "
b10 .
b10 :
1%
1+
#299000
0%
0+
#300000
b1 9
b1 "
b1 .
b1 :
1%
1+
#301000
0%
0+
#302000
12
15
b0 9
b0 "
b0 .
b0 :
1%
1+
#303000
0%
0+
#304000
02
05
b100 ;
b100 #
b100 ,
b100 <
b1001 9
b1001 "
b1001 .
b1001 :
1%
1+
#305000
0%
0+
#306000
b1000 9
b1000 "
b1000 .
b1000 :
1%
1+
#307000
0%
0+
#308000
b111 9
b111 "
b111 .
b111 :
1%
1+
#309000
0%
0+
#310000
b110 9
b110 "
b110 .
b110 :
1%
1+
#311000
0%
0+
#312000
b101 9
b101 "
b101 .
b101 :
1%
1+
#313000
0%
0+
#314000
b100 9
b100 "
b100 .
b100 :
1%
1+
#315000
0%
0+
#316000
b11 9
b11 "
b11 .
b11 :
1%
1+
#317000
0%
0+
#318000
b10 9
b10 "
b10 .
b10 :
1%
1+
#319000
0%
0+
#320000
b1 9
b1 "
b1 .
b1 :
1%
1+
#321000
0%
0+
#322000
12
15
b0 9
b0 "
b0 .
b0 :
1%
1+
#323000
0%
0+
#324000
02
05
b11 ;
b11 #
b11 ,
b11 <
b1001 9
b1001 "
b1001 .
b1001 :
1%
1+
#325000
0%
0+
#326000
b1000 9
b1000 "
b1000 .
b1000 :
1%
1+
#327000
0%
0+
#328000
b111 9
b111 "
b111 .
b111 :
1%
1+
#329000
0%
0+
#330000
b110 9
b110 "
b110 .
b110 :
1%
1+
#331000
0%
0+
#332000
b101 9
b101 "
b101 .
b101 :
1%
1+
#333000
0%
0+
#334000
b100 9
b100 "
b100 .
b100 :
1%
1+
#335000
0%
0+
#336000
b11 9
b11 "
b11 .
b11 :
1%
1+
#337000
0%
0+
#338000
b10 9
b10 "
b10 .
b10 :
1%
1+
#339000
0%
0+
#340000
b1 9
b1 "
b1 .
b1 :
1%
1+
#341000
0%
0+
#342000
12
15
b0 9
b0 "
b0 .
b0 :
1%
1+
#343000
0%
0+
#344000
02
05
b10 ;
b10 #
b10 ,
b10 <
b1001 9
b1001 "
b1001 .
b1001 :
1%
1+
#345000
0%
0+
#346000
b1000 9
b1000 "
b1000 .
b1000 :
1%
1+
#347000
0%
0+
#348000
b111 9
b111 "
b111 .
b111 :
1%
1+
#349000
0%
0+
#350000
b110 9
b110 "
b110 .
b110 :
1%
1+
#351000
0%
0+
#352000
b101 9
b101 "
b101 .
b101 :
1%
1+
#353000
0%
0+
#354000
b100 9
b100 "
b100 .
b100 :
1%
1+
#355000
0%
0+
#356000
b11 9
b11 "
b11 .
b11 :
1%
1+
#357000
0%
0+
#358000
b10 9
b10 "
b10 .
b10 :
1%
1+
#359000
0%
0+
#360000
b1 9
b1 "
b1 .
b1 :
1%
1+
#361000
0%
0+
#362000
12
15
b0 9
b0 "
b0 .
b0 :
1%
1+
#363000
0%
0+
#364000
02
05
b1 ;
b1 #
b1 ,
b1 <
b1001 9
b1001 "
b1001 .
b1001 :
1%
1+
#365000
0%
0+
#366000
b1000 9
b1000 "
b1000 .
b1000 :
1%
1+
#367000
0%
0+
#368000
b111 9
b111 "
b111 .
b111 :
1%
1+
#369000
0%
0+
#370000
b110 9
b110 "
b110 .
b110 :
1%
1+
#371000
0%
0+
#372000
b101 9
b101 "
b101 .
b101 :
1%
1+
#373000
0%
0+
#374000
b100 9
b100 "
b100 .
b100 :
1%
1+
#375000
0%
0+
#376000
b11 9
b11 "
b11 .
b11 :
1%
1+
#377000
0%
0+
#378000
b10 9
b10 "
b10 .
b10 :
1%
1+
#379000
0%
0+
#380000
b1 9
b1 "
b1 .
b1 :
1%
1+
#381000
0%
0+
#382000
12
15
b0 9
b0 "
b0 .
b0 :
1%
1+
#383000
0%
0+
#384000
02
16
05
b0 ;
b0 #
b0 ,
b0 <
b1001 9
b1001 "
b1001 .
b1001 :
1%
1+
#385000
0%
0+
#386000
b1000 9
b1000 "
b1000 .
b1000 :
1%
1+
#387000
0%
0+
#388000
b111 9
b111 "
b111 .
b111 :
1%
1+
#389000
0%
0+
#390000
b110 9
b110 "
b110 .
b110 :
1%
1+
#391000
0%
0+
#392000
b101 9
b101 "
b101 .
b101 :
1%
1+
#393000
0%
0+
#394000
b100 9
b100 "
b100 .
b100 :
1%
1+
#395000
0%
0+
#396000
b11 9
b11 "
b11 .
b11 :
1%
1+
#397000
0%
0+
#398000
b10 9
b10 "
b10 .
b10 :
1%
1+
#399000
0%
0+
#400000
b1 9
b1 "
b1 .
b1 :
1%
1+
#401000
0%
0+
#402000
13
12
15
b0 9
b0 "
b0 .
b0 :
1%
1+
#403000
0%
0+
#404000
03
02
06
05
b1000 =
b1000 !
b1000 -
b101 ;
b101 #
b101 ,
b101 <
b1001 9
b1001 "
b1001 .
b1001 :
1%
1+
#405000
0%
0+
#406000
b1000 9
b1000 "
b1000 .
b1000 :
1%
1+
#407000
0%
0+
#408000
b111 9
b111 "
b111 .
b111 :
1%
1+
#409000
0%
0+
#410000
b110 9
b110 "
b110 .
b110 :
1%
1+
#411000
0%
0+
#412000
b101 9
b101 "
b101 .
b101 :
1%
1+
#413000
0%
0+
#414000
b100 9
b100 "
b100 .
b100 :
1%
1+
#415000
0%
0+
#416000
b11 9
b11 "
b11 .
b11 :
1%
1+
#417000
0%
0+
#418000
b10 9
b10 "
b10 .
b10 :
1%
1+
#419000
0%
0+
#420000
b1 9
b1 "
b1 .
b1 :
1%
1+
#421000
0%
0+
#422000
12
15
b0 9
b0 "
b0 .
b0 :
1%
1+
#423000
0%
0+
#424000
02
05
b100 ;
b100 #
b100 ,
b100 <
b1001 9
b1001 "
b1001 .
b1001 :
1%
1+
#425000
0%
0+
#426000
b1000 9
b1000 "
b1000 .
b1000 :
1%
1+
#427000
0%
0+
#428000
b111 9
b111 "
b111 .
b111 :
1%
1+
#429000
0%
0+
#430000
b110 9
b110 "
b110 .
b110 :
1%
1+
#431000
0%
0+
#432000
b101 9
b101 "
b101 .
b101 :
1%
1+
#433000
0%
0+
#434000
b100 9
b100 "
b100 .
b100 :
1%
1+
#435000
0%
0+
#436000
b11 9
b11 "
b11 .
b11 :
1%
1+
#437000
0%
0+
#438000
b10 9
b10 "
b10 .
b10 :
1%
1+
#439000
0%
0+
#440000
b1 9
b1 "
b1 .
b1 :
1%
1+
#441000
0%
0+
#442000
12
15
b0 9
b0 "
b0 .
b0 :
1%
1+
#443000
0%
0+
#444000
02
05
b11 ;
b11 #
b11 ,
b11 <
b1001 9
b1001 "
b1001 .
b1001 :
1%
1+
#445000
0%
0+
#446000
b1000 9
b1000 "
b1000 .
b1000 :
1%
1+
#447000
0%
0+
#448000
b111 9
b111 "
b111 .
b111 :
1%
1+
#449000
0%
0+
#450000
b110 9
b110 "
b110 .
b110 :
1%
1+
#451000
0%
0+
#452000
b101 9
b101 "
b101 .
b101 :
1%
1+
#453000
0%
0+
#454000
b100 9
b100 "
b100 .
b100 :
1%
1+
#455000
0%
0+
#456000
b11 9
b11 "
b11 .
b11 :
1%
1+
#457000
0%
0+
#458000
b10 9
b10 "
b10 .
b10 :
1%
1+
#459000
0%
0+
#460000
b1 9
b1 "
b1 .
b1 :
1%
1+
#461000
0%
0+
#462000
12
15
b0 9
b0 "
b0 .
b0 :
1%
1+
#463000
0%
0+
#464000
02
05
b10 ;
b10 #
b10 ,
b10 <
b1001 9
b1001 "
b1001 .
b1001 :
1%
1+
#465000
0%
0+
#466000
b1000 9
b1000 "
b1000 .
b1000 :
1%
1+
#467000
0%
0+
#468000
b111 9
b111 "
b111 .
b111 :
1%
1+
#469000
0%
0+
#470000
b110 9
b110 "
b110 .
b110 :
1%
1+
#471000
0%
0+
#472000
b101 9
b101 "
b101 .
b101 :
1%
1+
#473000
0%
0+
#474000
b100 9
b100 "
b100 .
b100 :
1%
1+
#475000
0%
0+
#476000
b11 9
b11 "
b11 .
b11 :
1%
1+
#477000
0%
0+
#478000
b10 9
b10 "
b10 .
b10 :
1%
1+
#479000
0%
0+
#480000
b1 9
b1 "
b1 .
b1 :
1%
1+
#481000
0%
0+
#482000
12
15
b0 9
b0 "
b0 .
b0 :
1%
1+
#483000
0%
0+
#484000
02
05
b1 ;
b1 #
b1 ,
b1 <
b1001 9
b1001 "
b1001 .
b1001 :
1%
1+
#485000
0%
0+
#486000
b1000 9
b1000 "
b1000 .
b1000 :
1%
1+
#487000
0%
0+
#488000
b111 9
b111 "
b111 .
b111 :
1%
1+
#489000
0%
0+
#490000
b110 9
b110 "
b110 .
b110 :
1%
1+
#491000
0%
0+
#492000
b101 9
b101 "
b101 .
b101 :
1%
1+
#493000
0%
0+
#494000
b100 9
b100 "
b100 .
b100 :
1%
1+
#495000
0%
0+
#496000
b11 9
b11 "
b11 .
b11 :
1%
1+
#497000
0%
0+
