microwave/decoder/decoder.v
module decoder(
  input wire [3:0] minutes, second_tens, second_units,
  output reg [6:0] minutes_display, second_tens_display, second_units_display
);

    always @(*) begin
    case (minutes)
        4'b0000: minutes_display = 7'b0000001;
        4'b0001: minutes_display = 7'b1001111;
        4'b0010: minutes_display = 7'b0010010;
        4'b0011: minutes_display = 7'b0000110;
        4'b0100: minutes_display = 7'b1001100;
        4'b0101: minutes_display = 7'b0100100;
        4'b0110: minutes_display = 7'b0100000;
        4'b0111: minutes_display = 7'b0001101;
        4'b1000: minutes_display = 7'b0000000;
        4'b1001: minutes_display = 7'b0000100;
        default: minutes_display = 7'b0000000; // Off
    endcase

    case (second_tens)
        4'b0000: second_tens_display = 7'b0000001;
        4'b0001: second_tens_display = 7'b1001111;
        4'b0010: second_tens_display = 7'b0010010;
        4'b0011: second_tens_display = 7'b0000110;
        4'b0100: second_tens_display = 7'b1001100;
        4'b0101: second_tens_display = 7'b0100100;
        4'b0110: second_tens_display = 7'b0100000;
        4'b0111: second_tens_display = 7'b0001101;
        4'b1000: second_tens_display = 7'b0000000;
        4'b1001: second_tens_display = 7'b0000100;
        default: second_tens_display = 7'b0000000; // Off
    endcase

    case (second_units)
        4'b0000: second_units_display = 7'b0000001;
        4'b0001: second_units_display = 7'b1001111;
        4'b0010: second_units_display = 7'b0010010;
        4'b0011: second_units_display = 7'b0000110;
        4'b0100: second_units_display = 7'b1001100;
        4'b0101: second_units_display = 7'b0100100;
        4'b0110: second_units_display = 7'b0100000;
        4'b0111: second_units_display = 7'b0001101;
        4'b1000: second_units_display = 7'b0000000;
        4'b1001: second_units_display = 7'b0000100;
        default: second_units_display = 7'b0000000; // Off
    endcase
    end

endmodule

respostas/Q3/decoder/test_decoder.v
module tb_decoder;

  // Define inputs and outputs for the testbench
  reg [3:0] minutes;
  reg [3:0] second_tens;
  reg [3:0] second_units;
  wire [6:0] minutes_display;
  wire [6:0] second_tens_display;
  wire [6:0] second_units_display;

  // Instantiate the decoder module under test
  decoder dut (
    .minutes(minutes),
    .second_tens(second_tens),
    .second_units(second_units),
    .minutes_display(minutes_display),
    .second_tens_display(second_tens_display),
    .second_units_display(second_units_display)
  );

  // Initialize the VCD file
  initial begin
    $dumpfile("decoder_waveform.vcd"); // Specify the waveform file name
    $dumpvars(0, tb_decoder);  // Dump all variables
    // Initialize inputs
    minutes = 4'b0000;
    second_tens = 4'b0000;
    second_units = 4'b0000;

    // Simulation time steps
    #10;
    minutes = 4'b0001;
    #10;
    minutes = 4'b0010;
    #10;
    minutes = 4'b0011;
    #10;
    minutes = 4'b0100;
    #10;
    minutes = 4'b0101;
    #10;
    minutes = 4'b0110;
    #10;
    minutes = 4'b0111;
    #10;
    minutes = 4'b1000;
    #10;
    minutes = 4'b1001;
    #10;
    second_tens = 4'b0001;
    #10;
    second_tens = 4'b0010;
    #10;
    second_tens = 4'b0011;
    #10;
    second_tens = 4'b0100;
    #10;
    second_tens = 4'b0101;
    #10;
    second_tens = 4'b0110;
    #10;
    second_tens = 4'b0111;
    #10;
    second_tens = 4'b1000;
    #10;
    second_tens = 4'b1001;
    #10;
    second_units = 4'b0001;
    #10;
    second_units = 4'b0010;
    #10;
    second_units = 4'b0011;
    #10;
    second_units = 4'b0100;
    #10;
    second_units = 4'b0101;
    #10;
    second_units = 4'b0110;
    #10;
    second_units = 4'b0111;
    #10;
    second_units = 4'b1000;
    #10;
    second_units = 4'b1001;
    #10;

    // Add more test scenarios and stimulus code here

    // Monitor the outputs and display the results
    $display("Minutes Display: %b", minutes_display);
    $display("Second Tens Display: %b", second_tens_display);
    $display("Second Units Display: %b", second_units_display);

    // Add a simulation end condition (e.g., $finish;) when done testing
    $finish;
  end

endmodule

respostas/Q3/decoder/decoder_waveform.vcd
$date
	Sun Sep 24 18:43:40 2023
$end
$version
	Icarus Verilog
$end
$timescale
	1s
$end
$scope module tb_decoder $end
$var wire 7 ! second_units_display [6:0] $end
$var wire 7 " second_tens_display [6:0] $end
$var wire 7 # minutes_display [6:0] $end
$var reg 4 $ minutes [3:0] $end
$var reg 4 % second_tens [3:0] $end
$var reg 4 & second_units [3:0] $end
$scope module dut $end
$var wire 4 ' minutes [3:0] $end
$var wire 4 ( second_tens [3:0] $end
$var wire 4 ) second_units [3:0] $end
$var reg 7 * minutes_display [6:0] $end
$var reg 7 + second_tens_display [6:0] $end
$var reg 7 , second_units_display [6:0] $end
$upscope $end
$upscope $end
$enddefinitions $end
$comment Show the parameter values. $end
$dumpall
$end
#0
$dumpvars
b1 ,
b1 +
b1 *
b0 )
b0 (
b0 '
b0 &
b0 %
b0 $
b1 #
b1 "
b1 !
$end
#10
b1001111 #
b1001111 *
b1 $
b1 '
#20
b10010 #
b10010 *
b10 $
b10 '
#30
b110 #
b110 *
b11 $
b11 '
#40
b1001100 #
b1001100 *
b100 $
b100 '
#50
b100100 #
b100100 *
b101 $
b101 '
#60
b100000 #
b100000 *
b110 $
b110 '
#70
b1101 #
b1101 *
b111 $
b111 '
#80
b0 #
b0 *
b1000 $
b1000 '
#90
b100 #
b100 *
b1001 $
b1001 '
#100
b1001111 "
b1001111 +
b1 %
b1 (
#110
b10010 "
b10010 +
b10 %
b10 (
#120
b110 "
b110 +
b11 %
b11 (
#130
b1001100 "
b1001100 +
b100 %
b100 (
#140
b100100 "
b100100 +
b101 %
b101 (
#150
b100000 "
b100000 +
b110 %
b110 (
#160
b1101 "
b1101 +
b111 %
b111 (
#170
b0 "
b0 +
b1000 %
b1000 (
#180
b100 "
b100 +
b1001 %
b1001 (
#190
b1001111 !
b1001111 ,
b1 &
b1 )
#200
b10010 !
b10010 ,
b10 &
b10 )
#210
b110 !
b110 ,
b11 &
b11 )
#220
b1001100 !
b1001100 ,
b100 &
b100 )
#230
b100100 !
b100100 ,
b101 &
b101 )
#240
b100000 !
b100000 ,
b110 &
b110 )
#250
b1101 !
b1101 ,
b111 &
b111 )
#260
b0 !
b0 ,
b1000 &
b1000 )
#270
b100 !
b100 ,
b1001 &
b1001 )
