SD-Projeto3/SD-Projeto3/nivel1/nivel2/decodificador/decodificador.v
module decodificador(input wire [3:0] Minutos, DezenaSeg, Segundos,
                     output reg [6:0] OutMinutos, OutDezena, OutSegundos);
  
  always@(Minutos)
    case(Minutos)
      4'b0000 : OutMinutos = 7'b0000001;
      4'b0001 : OutMinutos = 7'b1001111;
      4'b0010 : OutMinutos = 7'b0010010;
      4'b0011 : OutMinutos = 7'b0000110;
      4'b0100 : OutMinutos = 7'b1001100;
      4'b0101 : OutMinutos = 7'b0100100;
      4'b0110 : OutMinutos = 7'b0100000;
      4'b0111 : OutMinutos = 7'b0001101;
      4'b1000 : OutMinutos = 7'b0000000;
      4'b1001 : OutMinutos = 7'b0000100;
    endcase
  
  always@(DezenaSeg)
  case(DezenaSeg)
      4'b0000 : OutDezena = 7'b0000001;
      4'b0001 : OutDezena = 7'b1001111;
      4'b0010 : OutDezena = 7'b0010010;
      4'b0011 : OutDezena = 7'b0000110;
      4'b0100 : OutDezena = 7'b1001100;
      4'b0101 : OutDezena = 7'b0100100;
      4'b0110 : OutDezena = 7'b0100000;
      4'b0111 : OutDezena = 7'b0001101;
      4'b1000 : OutDezena = 7'b0000000;
      4'b1001 : OutDezena = 7'b0000100;
    endcase
  
  always@(Segundos)
  case(Segundos)
      4'b0000 : OutSegundos = 7'b0000001;
      4'b0001 : OutSegundos = 7'b1001111;
      4'b0010 : OutSegundos = 7'b0010010;
      4'b0011 : OutSegundos = 7'b0000110;
      4'b0100 : OutSegundos = 7'b1001100;
      4'b0101 : OutSegundos = 7'b0100100;
      4'b0110 : OutSegundos = 7'b0100000;
      4'b0111 : OutSegundos = 7'b0001101;
      4'b1000 : OutSegundos = 7'b0000000;
      4'b1001 : OutSegundos = 7'b0000100;
    endcase
  
endmodule

SD-Projeto3/SD-Projeto3/nivel1/nivel2/decodificador/decodificador_teste.v
`timescale 1ns/1ns
`include "decodificador.v"

module decodificador_teste;

    reg [3:0] Minutos_TB, DezenaSeg_TB, Segundos_TB;
  	wire [6:0] OutMinutos_TB, OutDezena_TB, OutSegundos_TB;

  	decodificador DUT(.Minutos(Minutos_TB), .DezenaSeg(DezenaSeg_TB), .Segundos(Segundos_TB), .OutMinutos(OutMinutos_TB), .OutDezena(OutDezena_TB), .OutSegundos(OutSegundos_TB));

    initial
        begin

            $dumpfile("decodificador_teste.vcd");
            $dumpvars(0, decodificador_teste);

                Minutos_TB=4'b0000; DezenaSeg_TB=4'b0000; Segundos_TB=4'b0000;  
            #5  Minutos_TB=4'b0001; DezenaSeg_TB=4'b0001; Segundos_TB=4'b0001; 
         	  #5  Minutos_TB=4'b0010; DezenaSeg_TB=4'b0010; Segundos_TB=4'b0010;
            #5  Minutos_TB=4'b0011; DezenaSeg_TB=4'b0011; Segundos_TB=4'b0011;
            #5  Minutos_TB=4'b0100; DezenaSeg_TB=4'b0100; Segundos_TB=4'b0100;
            #5  Minutos_TB=4'b0101; DezenaSeg_TB=4'b0101; Segundos_TB=4'b0101;
          	#5  Minutos_TB=4'b0110; DezenaSeg_TB=4'b0110; Segundos_TB=4'b0110;
            #5  Minutos_TB=4'b0111; DezenaSeg_TB=4'b0111; Segundos_TB=4'b0111;
          	#5  Minutos_TB=4'b1000; DezenaSeg_TB=4'b1000; Segundos_TB=4'b1000;
            #5  Minutos_TB=4'b1001; DezenaSeg_TB=4'b1001; Segundos_TB=4'b1001;    
        end
endmodule

SD-Projeto3/SD-Projeto3/nivel1/nivel2/decodificador/decodificador_teste.vcd
$date
	Thu May 12 22:55:10 2022
$end
$version
	Icarus Verilog
$end
$timescale
	1ns
$end
$scope module decodificador_teste $end
$var wire 7 ! OutSegundos_TB [6:0] $end
$var wire 7 " OutMinutos_TB [6:0] $end
$var wire 7 # OutDezena_TB [6:0] $end
$var reg 4 $ DezenaSeg_TB [3:0] $end
$var reg 4 % Minutos_TB [3:0] $end
$var reg 4 & Segundos_TB [3:0] $end
$scope module DUT $end
$var wire 4 ' DezenaSeg [3:0] $end
$var wire 4 ( Minutos [3:0] $end
$var wire 4 ) Segundos [3:0] $end
$var reg 7 * OutDezena [6:0] $end
$var reg 7 + OutMinutos [6:0] $end
$var reg 7 , OutSegundos [6:0] $end
$upscope $end
$upscope $end
$enddefinitions $end
#0
$dumpvars
b1111110 ,
b1111110 +
b1111110 *
b0 )
b0 (
b0 '
b0 &
b0 %
b0 $
b1111110 #
b1111110 "
b1111110 !
$end
#5
b110000 !
b110000 ,
b110000 #
b110000 *
b110000 "
b110000 +
b1 &
b1 )
b1 $
b1 '
b1 %
b1 (
#10
b1101101 !
b1101101 ,
b1101101 #
b1101101 *
b1101101 "
b1101101 +
b10 &
b10 )
b10 $
b10 '
b10 %
b10 (
#15
b1111001 !
b1111001 ,
b1111001 #
b1111001 *
b1111001 "
b1111001 +
b11 &
b11 )
b11 $
b11 '
b11 %
b11 (
#20
b110011 !
b110011 ,
b110011 #
b110011 *
b110011 "
b110011 +
b100 &
b100 )
b100 $
b100 '
b100 %
b100 (
#25
b1011011 !
b1011011 ,
b1011011 #
b1011011 *
b1011011 "
b1011011 +
b101 &
b101 )
b101 $
b101 '
b101 %
b101 (
#30
b1011111 !
b1011111 ,
b1011111 #
b1011111 *
b1011111 "
b1011111 +
b110 &
b110 )
b110 $
b110 '
b110 %
b110 (
#35
b1110000 !
b1110000 ,
b1110000 #
b1110000 *
b1110000 "
b1110000 +
b111 &
b111 )
b111 $
b111 '
b111 %
b111 (
#40
b1111111 !
b1111111 ,
b1111111 #
b1111111 *
b1111111 "
b1111111 +
b1000 &
b1000 )
b1000 $
b1000 '
b1000 %
b1000 (
#45
b1111011 !
b1111011 ,
b1111011 #
b1111011 *
b1111011 "
b1111011 +
b1001 &
b1001 )
b1001 $
b1001 '
b1001 %
b1001 (
