SD-Projeto3/SD-Projeto3/nivel1/nivel2/magnetron/nivel3/circuito_logico/control_mag.v
module control_mag(input wire startn, stopn, clearn, door_closed, timer_done,
                output wire set, reset);

  assign set = (~startn) & door_closed & (~timer_done);
  assign reset = (~door_closed) | (~clearn) | (~stopn) | timer_done;

endmodule

SD-Projeto3/SD-Projeto3/nivel1/nivel2/magnetron/nivel3/circuito_logico/controle_mag_teste.v
`timescale 1ns/1ns
`include "control_mag.v"

module control_mag_teste;

    reg startn_TB, stopn_TB, clearn_TB, door_closed_TB, timer_done_TB;
  	wire  set_TB, reset_TB;

  	control_mag DUT(.startn(startn_TB), .stopn(stopn_TB), .clearn(clearn_TB), .door_closed(door_closed_TB), .timer_done(timer_done_TB), .set(set_TB), .reset(reset_TB));

    initial
        begin

            $dumpfile("control_mag_teste.vcd");
            $dumpvars(0, control_mag_teste);

                startn_TB=1; stopn_TB=0; clearn_TB=0; door_closed_TB=0; timer_done_TB=0;
            #5  startn_TB=1; stopn_TB=0; clearn_TB=0; door_closed_TB=1; timer_done_TB=0;
         	  #5  startn_TB=1; stopn_TB=1; clearn_TB=0; door_closed_TB=1; timer_done_TB=0;
            #5  startn_TB=1; stopn_TB=0; clearn_TB=0; door_closed_TB=1; timer_done_TB=0;
            #5  startn_TB=1; stopn_TB=0; clearn_TB=0; door_closed_TB=1; timer_done_TB=1;
            #5  startn_TB=1; stopn_TB=0; clearn_TB=0; door_closed_TB=0; timer_done_TB=0;
          	#5  startn_TB=1; stopn_TB=0; clearn_TB=1; door_closed_TB=1; timer_done_TB=1;
            #5  startn_TB=1; stopn_TB=0; clearn_TB=0; door_closed_TB=1; timer_done_TB=0;
          	#5  startn_TB=1; stopn_TB=1; clearn_TB=1; door_closed_TB=1; timer_done_TB=1;
            #5  startn_TB=0; stopn_TB=1; clearn_TB=1; door_closed_TB=1; timer_done_TB=1;
            #5  startn_TB=0; stopn_TB=0; clearn_TB=0; door_closed_TB=0; timer_done_TB=0;
          
        end
endmodule

SD-Projeto3/SD-Projeto3/nivel1/nivel2/magnetron/nivel3/circuito_logico/control_mag_teste.vcd
$date
	Mon Oct 17 12:41:09 2022
$end
$version
	Icarus Verilog
$end
$timescale
	1ns
$end
$scope module control_mag_teste $end
$var wire 1 ! reset_TB $end
$var wire 1 " set_TB $end
$var reg 1 # clearn_TB $end
$var reg 1 $ door_closed_TB $end
$var reg 1 % startn_TB $end
$var reg 1 & stopn_TB $end
$var reg 1 ' timer_done_TB $end
$scope module DUT $end
$var wire 1 ( clearn $end
$var wire 1 ) door_closed $end
$var wire 1 * startn $end
$var wire 1 + stopn $end
$var wire 1 , timer_done $end
$var reg 1 - reset $end
$var reg 1 . set $end
$upscope $end
$upscope $end
$enddefinitions $end
#0
$dumpvars
x.
1-
0,
0+
1*
0)
0(
0'
0&
1%
0$
0#
x"
1!
$end
#5
0-
0!
1.
1"
1$
1)
#10
1-
1!
1&
1+
#15
0-
0!
0&
0+
#20
1-
1!
1'
1,
#25
0'
0,
0$
0)
#30
1'
1,
1$
1)
1#
1(
#35
0-
0!
0'
0,
0#
0(
#40
1-
1!
1'
1,
1#
1(
1&
1+
#45
0%
0*
#50
0'
0,
0$
0)
0#
0(
0&
0+
