SD-Projeto3/SD-Projeto3/nivel1/nivel2/magnetron/nivel3/latch/latch.v
module latch(input wire set, reset,
            output reg Q);
  
  always@*
    if (set == 0 && reset == 0)
      begin
      Q <= Q;
      end
  	else if (set == 0 && reset == 1)
      begin
      Q <= 0;
      end
    else if (set == 1 && reset == 0)
      begin
      Q <= 1;
      end
    else if (set == 1 && reset == 1)
      begin
      Q <= 0;
      end
  
endmodule

SD-Projeto3/SD-Projeto3/nivel1/nivel2/magnetron/nivel3/latch/latch_teste.v
`timescale 1ns/1ps
`include "latch.v"

module latch_teste();

    reg settb, resettb;
    wire Qtb;

    latch DUT(.set(settb), .reset(resettb), .Q(Qtb));

    initial begin
        $dumpfile("latch_teste.vcd");
        $dumpvars(0,latch_teste);
            #10 settb = 0; resettb = 0;

            #10 settb = 0; resettb = 1;

            #10 settb = 0; resettb = 0;

            #10 settb = 1; resettb = 0;

            #10 settb = 0; resettb = 0;

            #10 settb = 1; resettb = 1;

            #10 settb = 0; resettb = 0;

            #10;
    end
endmodule

SD-Projeto3/SD-Projeto3/nivel1/nivel2/magnetron/nivel3/latch/latch_teste.vcd
$date
	Mon Oct 17 13:08:05 2022
$end
$version
	Icarus Verilog
$end
$timescale
	1ps
$end
$scope module latch_teste $end
$var wire 1 ! Qtb $end
$var reg 1 " resettb $end
$var reg 1 # settb $end
$scope module DUT $end
$var wire 1 $ reset $end
$var wire 1 % set $end
$var reg 1 & Q $end
$upscope $end
$upscope $end
$enddefinitions $end
#0
$dumpvars
x&
x%
x$
x#
x"
x!
$end
#10000
0"
0$
0#
0%
#20000
0&
0!
1"
1$
#30000
0"
0$
#40000
1&
1!
1#
1%
#50000
0#
0%
#60000
0&
0!
1"
1$
1#
1%
#70000
0"
0$
0#
0%
