nivel 3/SR_Latch.v
module SR_Latch (
    input wire S,         // Entrada Set
    input wire R,         // Entrada Reset
    output reg Q,         // Saída Q
    output reg Q_bar      // Saída complementar de Q (Q invertido)
);

    always @(S, R) begin
        if (R == 1'b0) begin
            Q <= 1'b0;   // Se R for 0, o latch é reset (Q = 0)
            Q_bar <= 1'b1;
        end else if (S == 1'b0) begin
            Q <= 1'b1;   // Se S for 0, o latch é set (Q = 1)
            Q_bar <= 1'b0;
        end
    end

endmodule

respostas/Q3/sr_latch/test_sr_latch.v
module test_sr_Latch;

  reg S;
  reg R;
  wire Q;
  wire Q_bar;

  // Instantiate the SR_Latch module under test
  sr_latch dut (
    .S(S),
    .R(R),
    .Q(Q),
    .Q_bar(Q_bar)
  );

  initial begin
    $dumpfile("waveform.vcd"); // Especifique o nome do arquivo de forma de onda
    $dumpvars(0, test_sr_Latch);  // Dump de todas as variáveis

    // Inicialize os sinais
    S = 0;
    R = 0;

    // Teste o comportamento do SR Latch
    #10 S = 1; // Defina o latch
    #10 R = 1; // Redefina o latch
    #10 S = 0; // Defina o latch novamente
    #10 R = 0; // Redefina o latch novamente
    #10 S = 1; // Defina o latch
    #10 R = 1; // Redefina o latch
    #10 S = 0; // Defina o latch novamente
    #10 R = 0;
    #10;      // Mantenha no estado atual

    // Encerre a simulação
    $finish;
  end

endmodule

respostas/Q2/sr_latch/waveform.vcd
$date
	Sat Sep 23 17:22:11 2023
$end
$version
	Icarus Verilog
$end
$timescale
	1s
$end
$scope module test_sr_Latch $end
$var wire 1 ! Q_bar $end
$var wire 1 " Q $end
$var reg 1 # R $end
$var reg 1 $ S $end
$scope module dut $end
$var wire 1 # R $end
$var wire 1 $ S $end
$var reg 1 " Q $end
$var reg 1 ! Q_bar $end
$upscope $end
$upscope $end
$enddefinitions $end
$comment Show the parameter values. $end
$dumpall
$end
#0
$dumpvars
0$
0#
x"
x!
$end
#10
0!
1"
1$
#20
1#
#30
1!
0"
0$
#40
0#
#50
0!
1"
1$
#60
1#
#70
1!
0"
0$
#80
0#
