SD-Projeto3/SD-Projeto3/nivel1/nivel2/contador/nivel3/contador_mod10/contador_mod10.v
module contador_mod10 (data, clk, load, en, clearn, count, tc, count_end);
  // 1) Adicionei o input count_end, ele vai servir para parar a contagem
  // regressiva quando os algarismos dos min, dez_seg e seg forem
  // iguais a 0, e não simplesmente fazer um loop infinito.
  // 2) Troquei count_end para ser um output, que vai indicar quando chegou a zero
  input wire [3:0] data;
  input wire clk, load, en, clearn;
  output reg [3:0] count;
  output wire tc; 
  output wire count_end;

  always @ (negedge clearn) // Lembrar de trocar o reset e o stop (feito)
  begin
    count = 4'b0000;
  end

  assign count_end = (count == 4'b0000) ? 1'b1 : 1'b0;
  assign tc = en & count_end;

  always @ (posedge clk)
  begin
    if (en) 
      case (count)
        4'b1001: begin
          count <= 4'b1000;
        end // 9 -> 8
        4'b0001: begin 
          count <= 4'b0000;
        end  // 1 -> 0
        4'b0000: begin
          count <= 4'b1001;
        end // 0 -> 9
        default: count <= count - 4'b0001;
      endcase

    else begin


      if(!load) // Lembrar q aq o valor do load tá invertido
        count <= data;
    end
  end
endmodule

SD-Projeto3/SD-Projeto3/nivel1/nivel2/contador/nivel3/contador_mod10/contador_mod10_teste.v
`include "contador_mod10.v"
`timescale 1ns/1ps

module contador_mod10_teste();

 	reg [3:0] data; 
  	reg clk, load, en, clearn;
  	wire [3:0] count; 
  	wire tc;
    wire count_endTB;
  	integer i;
  

  	contador_mod10 dut(data, clk, load, en, clearn, count, tc, count_endTB);

	initial
		begin
		
			$dumpfile("contador_mod10_teste.vcd");
			$dumpvars(0, contador_mod10_teste);
          
      assign load = 1;
      assign en = 0; 
      assign clearn = 1;
      assign data = 4'b0110;

      #5 assign load = 0;

      #5 assign load = 1;

      #5 assign en = 1; 
    end
  
  initial
    
    begin
    	clk = 1'b0;
  	end
		
  initial
    begin
    	#5 clk = ~clk;
      for(i = 0; i < 26; i= i + 1)
        begin
          #5 clk = ~clk;
        end
      
    end
    
endmodule

SD-Projeto3/SD-Projeto3/nivel1/nivel2/contador/nivel3/contador_mod10/contador_mod10_teste.vcd
$date
	Sat Oct 22 13:29:31 2022
$end
$version
	Icarus Verilog
$end
$timescale
	1ps
$end
$scope module contador_mod10_teste $end
$var wire 4 ! count [3:0] $end
$var wire 1 " count_endTB $end
$var wire 1 # tc $end
$var reg 1 $ clearn $end
$var reg 1 % clk $end
$var reg 4 & data [3:0] $end
$var reg 1 ' en $end
$var integer 32 ( i [31:0] $end
$var reg 1 ) load $end
$scope module dut $end
$var wire 1 * clearn $end
$var wire 1 + clk $end
$var wire 1 " count_end $end
$var wire 4 , data [3:0] $end
$var wire 1 - en $end
$var wire 1 . load $end
$var wire 1 # tc $end
$var reg 4 / count [3:0] $end
$upscope $end
$upscope $end
$enddefinitions $end
#0
$dumpvars
bx /
1.
0-
b110 ,
0+
1*
1)
bx (
0'
b110 &
0%
1$
0#
x"
bx !
$end
#5000
0"
b110 /
b110 !
b0 (
1%
1+
0)
0.
#10000
b1 (
0%
0+
1)
1.
#15000
b101 /
b101 !
b10 (
1%
1+
1'
1-
#20000
b11 (
0%
0+
#25000
b100 /
b100 !
b100 (
1%
1+
#30000
b101 (
0%
0+
#35000
b11 /
b11 !
b110 (
1%
1+
#40000
b111 (
0%
0+
#45000
b10 /
b10 !
b1000 (
1%
1+
#50000
b1001 (
0%
0+
#55000
b1 /
b1 !
b1010 (
1%
1+
#60000
b1011 (
0%
0+
#65000
1#
1"
b0 /
b0 !
b1100 (
1%
1+
#70000
b1101 (
0%
0+
#75000
0#
0"
b1001 /
b1001 !
b1110 (
1%
1+
#80000
b1111 (
0%
0+
#85000
b1000 /
b1000 !
b10000 (
1%
1+
#90000
b10001 (
0%
0+
#95000
b111 /
b111 !
b10010 (
1%
1+
#100000
b10011 (
0%
0+
#105000
b110 /
b110 !
b10100 (
1%
1+
#110000
b10101 (
0%
0+
#115000
b101 /
b101 !
b10110 (
1%
1+
#120000
b10111 (
0%
0+
#125000
b100 /
b100 !
b11000 (
1%
1+
#130000
b11001 (
0%
0+
#135000
b11 /
b11 !
b11010 (
1%
1+
