microwave/encoder/counter_0to7.v
module counter_0to7(input wire clear,
                    input wire clk,
                    output reg delay);


    reg [2:0] counter;

    always @(posedge clk or posedge clear) 
        begin 
        if (clear)
            begin
            counter = 3'b000;
            delay = 0;
            end
        else
            if (counter == 3)
            begin
            delay = 1;
            counter = counter + 1;
            end
            else if(counter < 7)
            begin
                counter = counter + 1;
            end
        end 
endmodule

microwave/encoder/test_counter_0to7.v
module test_counter_0to7;

  // Define inputs and outputs for the testbench
  reg clear;
  reg clk;
  wire delay;

  // Instantiate the counter_0to7 module under test
  counter_0to7 dut (
    .clear(clear),
    .clk(clk),
    .delay(delay)
  );

  // Clock generation
  always begin
    #5 clk = ~clk;
  end

  // Initialize the VCD file
  initial begin
    $dumpfile("counter_0to7_waveform.vcd"); // Specify the waveform file name
    $dumpvars(0, test_counter_0to7);  // Dump all variables
    // Initialize inputs
    clear = 0;
    clk = 0;

    // Simulate the counter operation
    // Add more test scenarios and stimulus code here

    // Example: Clear the counter
    clear = 1;
    #10 clear = 0;

    // Example: Clock the counter
    repeat (8) begin
      #5 clk = ~clk;
    end

    // Monitor the outputs and display the results
    // Add assertions or checks as needed

    // Add a simulation end condition (e.g., $finish;) when done testing
    $finish;
  end

endmodule

microwave/encoder/counter_0to7_waveform.vcd
$date
	Sun Sep 24 20:36:07 2023
$end
$version
	Icarus Verilog
$end
$timescale
	1s
$end
$scope module test_counter_0to7 $end
$var wire 1 ! delay $end
$var reg 1 " clear $end
$var reg 1 # clk $end
$scope module dut $end
$var wire 1 " clear $end
$var wire 1 # clk $end
$var reg 3 $ counter [2:0] $end
$var reg 1 ! delay $end
$upscope $end
$upscope $end
$enddefinitions $end
$comment Show the parameter values. $end
$dumpall
$end
#0
$dumpvars
b0 $
0#
1"
0!
$end
#5
1#
#10
0#
0"
#15
b1 $
0#
#20
b10 $
0#
#25
b11 $
0#
#30
b100 $
1!
0#
#35
b101 $
0#
#40
b110 $
0#
#45
b111 $
0#
