SD-Projeto3/SD-Projeto3/nivel1/nivel2/entrada_time/nivel3/mux/mux.v
module mux(input wire sel, saida_contador, Hz,
              output reg Q);
  
  always@*
  if (sel == 0)
    begin
      Q = saida_contador;
    end
  else
      Q = Hz;
  
endmodule

SD-Projeto3/SD-Projeto3/nivel1/nivel2/entrada_time/nivel3/cont_assincrono/counter_assin.v
module counter(input wire clock, clear, 
                output reg Q);
	
  reg [2:0] contador;
  always @(posedge clock or posedge clear) 
    begin 
      if (clear)
        begin
          contador = 3'b000;
          Q = 0;
        end
      else
        if (contador == 3)
          begin
           Q = 1;
           contador = contador + 1'b1;
          end
        else if(contador < 7)
          begin
            contador = contador + 1'b1;
          end
    end 
endmodule

SD-Projeto3/SD-Projeto3/nivel1/nivel2/entrada_time/nivel3/divisor_freq/divi.v
module divi(input clk,
            output reg clk100);
  reg [5:0] a = 6'b000000;
  initial clk100 = 1'b0;
  
  always@(posedge clk)
    begin
      a = a + 1'b1;
      
      if(a >= 50)
        begin
          a = 6'b000000;
          clk100 = ~clk100;
        end
    end
endmodule

SD-Projeto3/SD-Projeto3/nivel1/nivel2/entrada_time/nivel3/codificador_priori/codificador_priori.v
module codificador_priori(teclado, enablen, BCD);
  // Mudei o valor dos números binários para o normal
  input wire [9:0]teclado;
  input wire enablen;
  output reg [3:0]BCD;
  //output reg dado_valido;

  //initial dado_valido = 1'b0;

  always@(teclado)
    if (enablen == 1'b0)
      begin
        if (teclado[9:0] == 10'b1000000000)
          begin
        	  BCD = 4'b1001;
        	  //dado_valido = 1'b1;
          end
        else if (teclado[9:0] == 10'b0100000000)
          begin
        	  BCD = 4'b1000;
            //dado_valido = 1'b1;
          end
        else if (teclado[9:0] == 10'b0010000000)
          begin
			      BCD = 4'b0111;
        	  //dado_valido = 1'b1;
          end
        else if (teclado[9:0] == 10'b0001000000)
          begin
            BCD = 4'b0110;
            //dado_valido = 1'b1;
          end 
        else if (teclado[9:0] == 10'b0000100000)
          begin 
			      BCD = 4'b0101;
            //dado_valido = 1'b1;
          end 
        else if (teclado[9:0] == 10'b0000010000)
          begin
			      BCD = 4'b0100;
            //dado_valido = 1'b1;
          end 
        else if (teclado[9:0] == 10'b0000001000)
          begin
			      BCD = 4'b0011;
            //dado_valido = 1'b1;
          end 
        else if (teclado[9:0] == 10'b0000000100)
          begin 
			      BCD = 4'b0010;
            //dado_valido = 1'b1;
          end 
        else if (teclado[9:0] == 10'b0000000010)
          begin 
			      BCD = 4'b0001;
            //dado_valido = 1'b1;
          end 
        else if (teclado[9:0] == 10'b0000000001)
          begin
			      BCD = 4'b0000;
            //dado_valido = 1'b1;
          end

  	end
endmodule

SD-Projeto3/SD-Projeto3/nivel1/nivel2/entrada_time/entrada_time_nivel2.v
`include "nivel2/entrada_time/nivel3/codificador_priori/codificador_priori.v"
`include "nivel2/entrada_time/nivel3/cont_assincrono/counter_assin.v"
`include "nivel2/entrada_time/nivel3/divisor_freq/divi.v"
`include "nivel2/entrada_time/nivel3/mux/mux.v"
// (Mudar o endereço dos arquivos se for fazer teste local)

module entrada_time_nivel2(input [9:0] keypad,
    input enablen,
    input clk,
    output [3:0] D,
    output loadn,
    output pgt_1Hz);

    wire clk100, Q;
    
    // Ao invés do codificador de prioridade ter o loadn como saída,
    // ele já é decidido por fora, ou seja, no nível 2,
    // quando é detectado se uma tecla foi pressionada ou não.
    reg keypad_pressed;
    
    initial keypad_pressed = 0;

    always @(keypad) begin
        if(keypad == 10'b00000_00000)
            keypad_pressed <= 0;
        else
            keypad_pressed <= 1;
    end

    assign loadn = ~keypad_pressed;

    codificador_priori codificador_priori(keypad, enablen, D);
    divi divi(clk, clk100);
    counter counter(clk, loadn, Q);
    mux mux(enablen, Q, clk100, pgt_1Hz);


endmodule

SD-Projeto3/SD-Projeto3/nivel1/nivel2/entrada_time/entrada_time_nivel2_teste.v
`timescale 1ns/1ps
`include "entrada_time_nivel2.v"

module entrada_time_nivel2_teste();

    reg [9:0] keypad;
    reg enablen;
    reg clk;
    wire [3:0] D;
    wire loadn;
    wire pgt_1Hz;

    entrada_time_nivel2 DUT(
        .keypad(keypad),
        .enablen(enablen),
        .clk(clk),
        .D(D),
        .loadn(loadn),
        .pgt_1Hz(pgt_1Hz)
    );

    initial begin
        $dumpfile("entrada_time_nivel2_teste.vcd");
        $dumpvars(0, entrada_time_nivel2_teste);

            #1 keypad = 10'b1000000000;
            clk = 1;
            enablen = 0;
            repeat(201)
                #1 clk = ~clk;
            
            #1 keypad = 10'b0100000000;
            clk = 1;
            repeat(201)
                #1 clk = ~clk;

            #1 keypad = 10'b100000000;
            clk = 1;
            enablen = 1;
            repeat(201)
                #1 clk = ~clk;

            enablen = 0;
            repeat(201)
                #1 clk = ~clk;
            
    end
endmodule

SD-Projeto3/SD-Projeto3/nivel1/nivel2/entrada_time/entrada_time_nivel2_teste.vcd
$date
	Sat Oct 22 10:20:01 2022
$end
$version
	Icarus Verilog
$end
$timescale
	1ps
$end
$scope module entrada_time_nivel2_teste $end
$var wire 4 ! D [3:0] $end
$var wire 1 " loadn $end
$var wire 1 # pgt_1Hz $end
$var reg 1 $ clk $end
$var reg 1 % enablen $end
$var reg 10 & keypad [9:0] $end
$scope module DUT $end
$var wire 4 ' D [3:0] $end
$var wire 1 ( Q $end
$var wire 1 ) clk $end
$var wire 1 * clk100 $end
$var wire 1 + enablen $end
$var wire 10 , keypad [9:0] $end
$var wire 1 " loadn $end
$var wire 1 # pgt_1Hz $end
$var reg 1 - keypad_pressed $end
$scope module codificador_priori $end
$var wire 1 + enablen $end
$var wire 10 . teclado [9:0] $end
$var reg 4 / BCD [3:0] $end
$upscope $end
$scope module divi $end
$var wire 1 ) clk $end
$var reg 6 0 a [5:0] $end
$var reg 1 1 clk100 $end
$upscope $end
$scope module counter $end
$var wire 1 " clear $end
$var wire 1 ) clock $end
$var reg 1 2 Q $end
$var reg 3 3 contador [2:0] $end
$upscope $end
$scope module mux $end
$var wire 1 * Hz $end
$var wire 1 ( saida_contador $end
$var wire 1 + sel $end
$var reg 1 4 Q $end
$upscope $end
$upscope $end
$upscope $end
$enddefinitions $end
#0
$dumpvars
04
b0 3
02
01
b0 0
bx /
bx .
0-
bx ,
x+
0*
x)
0(
bx '
bx &
x%
x$
0#
1"
bx !
$end
#1000
0"
1-
b1 0
b1001 /
b1001 !
b1001 '
0%
0+
1$
1)
b1000000000 &
b1000000000 ,
b1000000000 .
#2000
0$
0)
#3000
b1 3
b10 0
1$
1)
#4000
0$
0)
#5000
b10 3
b11 0
1$
1)
#6000
0$
0)
#7000
b11 3
b100 0
1$
1)
#8000
0$
0)
#9000
14
1#
b100 3
12
1(
b101 0
1$
1)
#10000
0$
0)
#11000
b101 3
b110 0
1$
1)
#12000
0$
0)
#13000
b110 3
b111 0
1$
1)
#14000
0$
0)
#15000
b111 3
b1000 0
1$
1)
#16000
0$
0)
#17000
b1001 0
1$
1)
#18000
0$
0)
#19000
b1010 0
1$
1)
#20000
0$
0)
#21000
b1011 0
1$
1)
#22000
0$
0)
#23000
b1100 0
1$
1)
#24000
0$
0)
#25000
b1101 0
1$
1)
#26000
0$
0)
#27000
b1110 0
1$
1)
#28000
0$
0)
#29000
b1111 0
1$
1)
#30000
0$
0)
#31000
b10000 0
1$
1)
#32000
0$
0)
#33000
b10001 0
1$
1)
#34000
0$
0)
#35000
b10010 0
1$
1)
#36000
0$
0)
#37000
b10011 0
1$
1)
#38000
0$
0)
#39000
b10100 0
1$
1)
#40000
0$
0)
#41000
b10101 0
1$
1)
#42000
0$
0)
#43000
b10110 0
1$
1)
#44000
0$
0)
#45000
b10111 0
1$
1)
#46000
0$
0)
#47000
b11000 0
1$
1)
#48000
0$
0)
#49000
b11001 0
1$
1)
#50000
0$
0)
#51000
b11010 0
1$
1)
#52000
0$
0)
#53000
b11011 0
1$
1)
#54000
0$
0)
#55000
b11100 0
1$
1)
#56000
0$
0)
#57000
b11101 0
1$
1)
#58000
0$
0)
#59000
b11110 0
1$
1)
#60000
0$
0)
#61000
b11111 0
1$
1)
#62000
0$
0)
#63000
b100000 0
1$
1)
#64000
0$
0)
#65000
b100001 0
1$
1)
#66000
0$
0)
#67000
b100010 0
1$
1)
#68000
0$
0)
#69000
b100011 0
1$
1)
#70000
0$
0)
#71000
b100100 0
1$
1)
#72000
0$
0)
#73000
b100101 0
1$
1)
#74000
0$
0)
#75000
b100110 0
1$
1)
#76000
0$
0)
#77000
b100111 0
1$
1)
#78000
0$
0)
#79000
b101000 0
1$
1)
#80000
0$
0)
#81000
b101001 0
1$
1)
#82000
0$
0)
#83000
b101010 0
1$
1)
#84000
0$
0)
#85000
b101011 0
1$
1)
#86000
0$
0)
#87000
b101100 0
1$
1)
#88000
0$
0)
#89000
b101101 0
1$
1)
#90000
0$
0)
#91000
b101110 0
1$
1)
#92000
0$
0)
#93000
b101111 0
1$
1)
#94000
0$
0)
#95000
b110000 0
1$
1)
#96000
0$
0)
#97000
b110001 0
1$
1)
#98000
0$
0)
#99000
11
1*
b0 0
1$
1)
#100000
0$
0)
#101000
b1 0
1$
1)
#102000
0$
0)
#103000
b10 0
1$
1)
#104000
0$
0)
#105000
b11 0
1$
1)
#106000
0$
0)
#107000
b100 0
1$
1)
#108000
0$
0)
#109000
b101 0
1$
1)
#110000
0$
0)
#111000
b110 0
1$
1)
#112000
0$
0)
#113000
b111 0
1$
1)
#114000
0$
0)
#115000
b1000 0
1$
1)
#116000
0$
0)
#117000
b1001 0
1$
1)
#118000
0$
0)
#119000
b1010 0
1$
1)
#120000
0$
0)
#121000
b1011 0
1$
1)
#122000
0$
0)
#123000
b1100 0
1$
1)
#124000
0$
0)
#125000
b1101 0
1$
1)
#126000
0$
0)
#127000
b1110 0
1$
1)
#128000
0$
0)
#129000
b1111 0
1$
1)
#130000
0$
0)
#131000
b10000 0
1$
1)
#132000
0$
0)
#133000
b10001 0
1$
1)
#134000
0$
0)
#135000
b10010 0
1$
1)
#136000
0$
0)
#137000
b10011 0
1$
1)
#138000
0$
0)
#139000
b10100 0
1$
1)
#140000
0$
0)
#141000
b10101 0
1$
1)
#142000
0$
0)
#143000
b10110 0
1$
1)
#144000
0$
0)
#145000
b10111 0
1$
1)
#146000
0$
0)
#147000
b11000 0
1$
1)
#148000
0$
0)
#149000
b11001 0
1$
1)
#150000
0$
0)
#151000
b11010 0
1$
1)
#152000
0$
0)
#153000
b11011 0
1$
1)
#154000
0$
0)
#155000
b11100 0
1$
1)
#156000
0$
0)
#157000
b11101 0
1$
1)
#158000
0$
0)
#159000
b11110 0
1$
1)
#160000
0$
0)
#161000
b11111 0
1$
1)
#162000
0$
0)
#163000
b100000 0
1$
1)
#164000
0$
0)
#165000
b100001 0
1$
1)
#166000
0$
0)
#167000
b100010 0
1$
1)
#168000
0$
0)
#169000
b100011 0
1$
1)
#170000
0$
0)
#171000
b100100 0
1$
1)
#172000
0$
0)
#173000
b100101 0
1$
1)
#174000
0$
0)
#175000
b100110 0
1$
1)
#176000
0$
0)
#177000
b100111 0
1$
1)
#178000
0$
0)
#179000
b101000 0
1$
1)
#180000
0$
0)
#181000
b101001 0
1$
1)
#182000
0$
0)
#183000
b101010 0
1$
1)
#184000
0$
0)
#185000
b101011 0
1$
1)
#186000
0$
0)
#187000
b101100 0
1$
1)
#188000
0$
0)
#189000
b101101 0
1$
1)
#190000
0$
0)
#191000
b101110 0
1$
1)
#192000
0$
0)
#193000
b101111 0
1$
1)
#194000
0$
0)
#195000
b110000 0
1$
1)
#196000
0$
0)
#197000
b110001 0
1$
1)
#198000
0$
0)
#199000
01
0*
b0 0
1$
1)
#200000
0$
0)
#201000
b1 0
1$
1)
#202000
0$
0)
#203000
b10 0
b1000 /
b1000 !
b1000 '
1$
1)
b100000000 &
b100000000 ,
b100000000 .
#204000
0$
0)
#205000
b11 0
1$
1)
#206000
0$
0)
#207000
b100 0
1$
1)
#208000
0$
0)
#209000
b101 0
1$
1)
#210000
0$
0)
#211000
b110 0
1$
1)
#212000
0$
0)
#213000
b111 0
1$
1)
#214000
0$
0)
#215000
b1000 0
1$
1)
#216000
0$
0)
#217000
b1001 0
1$
1)
#218000
0$
0)
#219000
b1010 0
1$
1)
#220000
0$
0)
#221000
b1011 0
1$
1)
#222000
0$
0)
#223000
b1100 0
1$
1)
#224000
0$
0)
#225000
b1101 0
1$
1)
#226000
0$
0)
#227000
b1110 0
1$
1)
#228000
0$
0)
#229000
b1111 0
1$
1)
#230000
0$
0)
#231000
b10000 0
1$
1)
#232000
0$
0)
#233000
b10001 0
1$
1)
#234000
0$
0)
#235000
b10010 0
1$
1)
#236000
0$
0)
#237000
b10011 0
1$
1)
#238000
0$
0)
#239000
b10100 0
1$
1)
#240000
0$
0)
#241000
b10101 0
1$
1)
#242000
0$
0)
#243000
b10110 0
1$
1)
#244000
0$
0)
#245000
b10111 0
1$
1)
#246000
0$
0)
#247000
b11000 0
1$
1)
#248000
0$
0)
#249000
b11001 0
1$
1)
#250000
0$
0)
#251000
b11010 0
1$
1)
#252000
0$
0)
#253000
b11011 0
1$
1)
#254000
0$
0)
#255000
b11100 0
1$
1)
#256000
0$
0)
#257000
b11101 0
1$
1)
#258000
0$
0)
#259000
b11110 0
1$
1)
#260000
0$
0)
#261000
b11111 0
1$
1)
#262000
0$
0)
#263000
b100000 0
1$
1)
#264000
0$
0)
#265000
b100001 0
1$
1)
#266000
0$
0)
#267000
b100010 0
1$
1)
#268000
0$
0)
#269000
b100011 0
1$
1)
#270000
0$
0)
#271000
b100100 0
1$
1)
#272000
0$
0)
#273000
b100101 0
1$
1)
#274000
0$
0)
#275000
b100110 0
1$
1)
#276000
0$
0)
#277000
b100111 0
1$
1)
#278000
0$
0)
#279000
b101000 0
1$
1)
#280000
0$
0)
#281000
b101001 0
1$
1)
#282000
0$
0)
#283000
b101010 0
1$
1)
#284000
0$
0)
#285000
b101011 0
1$
1)
#286000
0$
0)
#287000
b101100 0
1$
1)
#288000
0$
0)
#289000
b101101 0
1$
1)
#290000
0$
0)
#291000
b101110 0
1$
1)
#292000
0$
0)
#293000
b101111 0
1$
1)
#294000
0$
0)
#295000
b110000 0
1$
1)
#296000
0$
0)
#297000
b110001 0
1$
1)
#298000
0$
0)
#299000
11
1*
b0 0
1$
1)
#300000
0$
0)
#301000
b1 0
1$
1)
#302000
0$
0)
#303000
b10 0
1$
1)
#304000
0$
0)
#305000
b11 0
1$
1)
#306000
0$
0)
#307000
b100 0
1$
1)
#308000
0$
0)
#309000
b101 0
1$
1)
#310000
0$
0)
#311000
b110 0
1$
1)
#312000
0$
0)
#313000
b111 0
1$
1)
#314000
0$
0)
#315000
b1000 0
1$
1)
#316000
0$
0)
#317000
b1001 0
1$
1)
#318000
0$
0)
#319000
b1010 0
1$
1)
#320000
0$
0)
#321000
b1011 0
1$
1)
#322000
0$
0)
#323000
b1100 0
1$
1)
#324000
0$
0)
#325000
b1101 0
1$
1)
#326000
0$
0)
#327000
b1110 0
1$
1)
#328000
0$
0)
#329000
b1111 0
1$
1)
#330000
0$
0)
#331000
b10000 0
1$
1)
#332000
0$
0)
#333000
b10001 0
1$
1)
#334000
0$
0)
#335000
b10010 0
1$
1)
#336000
0$
0)
#337000
b10011 0
1$
1)
#338000
0$
0)
#339000
b10100 0
1$
1)
#340000
0$
0)
#341000
b10101 0
1$
1)
#342000
0$
0)
#343000
b10110 0
1$
1)
#344000
0$
0)
#345000
b10111 0
1$
1)
#346000
0$
0)
#347000
b11000 0
1$
1)
#348000
0$
0)
#349000
b11001 0
1$
1)
#350000
0$
0)
#351000
b11010 0
1$
1)
#352000
0$
0)
#353000
b11011 0
1$
1)
#354000
0$
0)
#355000
b11100 0
1$
1)
#356000
0$
0)
#357000
b11101 0
1$
1)
#358000
0$
0)
#359000
b11110 0
1$
1)
#360000
0$
0)
#361000
b11111 0
1$
1)
#362000
0$
0)
#363000
b100000 0
1$
1)
#364000
0$
0)
#365000
b100001 0
1$
1)
#366000
0$
0)
#367000
b100010 0
1$
1)
#368000
0$
0)
#369000
b100011 0
1$
1)
#370000
0$
0)
#371000
b100100 0
1$
1)
#372000
0$
0)
#373000
b100101 0
1$
1)
#374000
0$
0)
#375000
b100110 0
1$
1)
#376000
0$
0)
#377000
b100111 0
1$
1)
#378000
0$
0)
#379000
b101000 0
1$
1)
#380000
0$
0)
#381000
b101001 0
1$
1)
#382000
0$
0)
#383000
b101010 0
1$
1)
#384000
0$
0)
#385000
b101011 0
1$
1)
#386000
0$
0)
#387000
b101100 0
1$
1)
#388000
0$
0)
#389000
b101101 0
1$
1)
#390000
0$
0)
#391000
b101110 0
1$
1)
#392000
0$
0)
#393000
b101111 0
1$
1)
#394000
0$
0)
#395000
b110000 0
1$
1)
#396000
0$
0)
#397000
b110001 0
1$
1)
#398000
0$
0)
#399000
01
0*
b0 0
1$
1)
#400000
0$
0)
#401000
b1 0
1$
1)
#402000
0$
0)
#403000
b10 0
1$
1)
#404000
0$
0)
#405000
04
0#
b11 0
1%
1+
1$
1)
#406000
0$
0)
#407000
b100 0
1$
1)
#408000
0$
0)
#409000
b101 0
1$
1)
#410000
0$
0)
#411000
b110 0
1$
1)
#412000
0$
0)
#413000
b111 0
1$
1)
#414000
0$
0)
#415000
b1000 0
1$
1)
#416000
0$
0)
#417000
b1001 0
1$
1)
#418000
0$
0)
#419000
b1010 0
1$
1)
#420000
0$
0)
#421000
b1011 0
1$
1)
#422000
0$
0)
#423000
b1100 0
1$
1)
#424000
0$
0)
#425000
b1101 0
1$
1)
#426000
0$
0)
#427000
b1110 0
1$
1)
#428000
0$
0)
#429000
b1111 0
1$
1)
#430000
0$
0)
#431000
b10000 0
1$
1)
#432000
0$
0)
#433000
b10001 0
1$
1)
#434000
0$
0)
#435000
b10010 0
1$
1)
#436000
0$
0)
#437000
b10011 0
1$
1)
#438000
0$
0)
#439000
b10100 0
1$
1)
#440000
0$
0)
#441000
b10101 0
1$
1)
#442000
0$
0)
#443000
b10110 0
1$
1)
#444000
0$
0)
#445000
b10111 0
1$
1)
#446000
0$
0)
#447000
b11000 0
1$
1)
#448000
0$
0)
#449000
b11001 0
1$
1)
#450000
0$
0)
#451000
b11010 0
1$
1)
#452000
0$
0)
#453000
b11011 0
1$
1)
#454000
0$
0)
#455000
b11100 0
1$
1)
#456000
0$
0)
#457000
b11101 0
1$
1)
#458000
0$
0)
#459000
b11110 0
1$
1)
#460000
0$
0)
#461000
b11111 0
1$
1)
#462000
0$
0)
#463000
b100000 0
1$
1)
#464000
0$
0)
#465000
b100001 0
1$
1)
#466000
0$
0)
#467000
b100010 0
1$
1)
#468000
0$
0)
#469000
b100011 0
1$
1)
#470000
0$
0)
#471000
b100100 0
1$
1)
#472000
0$
0)
#473000
b100101 0
1$
1)
#474000
0$
0)
#475000
b100110 0
1$
1)
#476000
0$
0)
#477000
b100111 0
1$
1)
#478000
0$
0)
#479000
b101000 0
1$
1)
#480000
0$
0)
#481000
b101001 0
1$
1)
#482000
0$
0)
#483000
b101010 0
1$
1)
#484000
0$
0)
#485000
b101011 0
1$
1)
#486000
0$
0)
#487000
b101100 0
1$
1)
#488000
0$
0)
#489000
b101101 0
1$
1)
#490000
0$
0)
#491000
b101110 0
1$
1)
#492000
0$
0)
#493000
b101111 0
1$
1)
#494000
0$
0)
#495000
b110000 0
1$
1)
#496000
0$
0)
#497000
b110001 0
1$
1)
#498000
0$
0)
#499000
14
1#
11
1*
b0 0
1$
1)
#500000
0$
0)
#501000
b1 0
1$
1)
#502000
0$
0)
#503000
b10 0
1$
1)
#504000
0$
0)
#505000
b11 0
1$
1)
#506000
0$
0)
#507000
b100 0
1$
1)
#508000
0$
0)
#509000
b101 0
1$
1)
#510000
0$
0)
#511000
b110 0
1$
1)
#512000
0$
0)
#513000
b111 0
1$
1)
#514000
0$
0)
#515000
b1000 0
1$
1)
#516000
0$
0)
#517000
b1001 0
1$
1)
#518000
0$
0)
#519000
b1010 0
1$
1)
#520000
0$
0)
#521000
b1011 0
1$
1)
#522000
0$
0)
#523000
b1100 0
1$
1)
#524000
0$
0)
#525000
b1101 0
1$
1)
#526000
0$
0)
#527000
b1110 0
1$
1)
#528000
0$
0)
#529000
b1111 0
1$
1)
#530000
0$
0)
#531000
b10000 0
1$
1)
#532000
0$
0)
#533000
b10001 0
1$
1)
#534000
0$
0)
#535000
b10010 0
1$
1)
#536000
0$
0)
#537000
b10011 0
1$
1)
#538000
0$
0)
#539000
b10100 0
1$
1)
#540000
0$
0)
#541000
b10101 0
1$
1)
#542000
0$
0)
#543000
b10110 0
1$
1)
#544000
0$
0)
#545000
b10111 0
1$
1)
#546000
0$
0)
#547000
b11000 0
1$
1)
#548000
0$
0)
#549000
b11001 0
1$
1)
#550000
0$
0)
#551000
b11010 0
1$
1)
#552000
0$
0)
#553000
b11011 0
1$
1)
#554000
0$
0)
#555000
b11100 0
1$
1)
#556000
0$
0)
#557000
b11101 0
1$
1)
#558000
0$
0)
#559000
b11110 0
1$
1)
#560000
0$
0)
#561000
b11111 0
1$
1)
#562000
0$
0)
#563000
b100000 0
1$
1)
#564000
0$
0)
#565000
b100001 0
1$
1)
#566000
0$
0)
#567000
b100010 0
1$
1)
#568000
0$
0)
#569000
b100011 0
1$
1)
#570000
0$
0)
#571000
b100100 0
1$
1)
#572000
0$
0)
#573000
b100101 0
1$
1)
#574000
0$
0)
#575000
b100110 0
1$
1)
#576000
0$
0)
#577000
b100111 0
1$
1)
#578000
0$
0)
#579000
b101000 0
1$
1)
#580000
0$
0)
#581000
b101001 0
1$
1)
#582000
0$
0)
#583000
b101010 0
1$
1)
#584000
0$
0)
#585000
b101011 0
1$
1)
#586000
0$
0)
#587000
b101100 0
1$
1)
#588000
0$
0)
#589000
b101101 0
1$
1)
#590000
0$
0)
#591000
b101110 0
1$
1)
#592000
0$
0)
#593000
b101111 0
1$
1)
#594000
0$
0)
#595000
b110000 0
1$
1)
#596000
0$
0)
#597000
b110001 0
1$
1)
#598000
0$
0)
#599000
04
0#
01
0*
b0 0
1$
1)
#600000
0$
0)
#601000
b1 0
1$
1)
#602000
0$
0)
#603000
b10 0
1$
1)
#604000
0$
0)
#605000
b11 0
1$
1)
#606000
14
1#
0%
0+
0$
0)
#607000
b100 0
1$
1)
#608000
0$
0)
#609000
b101 0
1$
1)
#610000
0$
0)
#611000
b110 0
1$
1)
#612000
0$
0)
#613000
b111 0
1$
1)
#614000
0$
0)
#615000
b1000 0
1$
1)
#616000
0$
0)
#617000
b1001 0
1$
1)
#618000
0$
0)
#619000
b1010 0
1$
1)
#620000
0$
0)
#621000
b1011 0
1$
1)
#622000
0$
0)
#623000
b1100 0
1$
1)
#624000
0$
0)
#625000
b1101 0
1$
1)
#626000
0$
0)
#627000
b1110 0
1$
1)
#628000
0$
0)
#629000
b1111 0
1$
1)
#630000
0$
0)
#631000
b10000 0
1$
1)
#632000
0$
0)
#633000
b10001 0
1$
1)
#634000
0$
0)
#635000
b10010 0
1$
1)
#636000
0$
0)
#637000
b10011 0
1$
1)
#638000
0$
0)
#639000
b10100 0
1$
1)
#640000
0$
0)
#641000
b10101 0
1$
1)
#642000
0$
0)
#643000
b10110 0
1$
1)
#644000
0$
0)
#645000
b10111 0
1$
1)
#646000
0$
0)
#647000
b11000 0
1$
1)
#648000
0$
0)
#649000
b11001 0
1$
1)
#650000
0$
0)
#651000
b11010 0
1$
1)
#652000
0$
0)
#653000
b11011 0
1$
1)
#654000
0$
0)
#655000
b11100 0
1$
1)
#656000
0$
0)
#657000
b11101 0
1$
1)
#658000
0$
0)
#659000
b11110 0
1$
1)
#660000
0$
0)
#661000
b11111 0
1$
1)
#662000
0$
0)
#663000
b100000 0
1$
1)
#664000
0$
0)
#665000
b100001 0
1$
1)
#666000
0$
0)
#667000
b100010 0
1$
1)
#668000
0$
0)
#669000
b100011 0
1$
1)
#670000
0$
0)
#671000
b100100 0
1$
1)
#672000
0$
0)
#673000
b100101 0
1$
1)
#674000
0$
0)
#675000
b100110 0
1$
1)
#676000
0$
0)
#677000
b100111 0
1$
1)
#678000
0$
0)
#679000
b101000 0
1$
1)
#680000
0$
0)
#681000
b101001 0
1$
1)
#682000
0$
0)
#683000
b101010 0
1$
1)
#684000
0$
0)
#685000
b101011 0
1$
1)
#686000
0$
0)
#687000
b101100 0
1$
1)
#688000
0$
0)
#689000
b101101 0
1$
1)
#690000
0$
0)
#691000
b101110 0
1$
1)
#692000
0$
0)
#693000
b101111 0
1$
1)
#694000
0$
0)
#695000
b110000 0
1$
1)
#696000
0$
0)
#697000
b110001 0
1$
1)
#698000
0$
0)
#699000
11
1*
b0 0
1$
1)
#700000
0$
0)
#701000
b1 0
1$
1)
#702000
0$
0)
#703000
b10 0
1$
1)
#704000
0$
0)
#705000
b11 0
1$
1)
#706000
0$
0)
#707000
b100 0
1$
1)
#708000
0$
0)
#709000
b101 0
1$
1)
#710000
0$
0)
#711000
b110 0
1$
1)
#712000
0$
0)
#713000
b111 0
1$
1)
#714000
0$
0)
#715000
b1000 0
1$
1)
#716000
0$
0)
#717000
b1001 0
1$
1)
#718000
0$
0)
#719000
b1010 0
1$
1)
#720000
0$
0)
#721000
b1011 0
1$
1)
#722000
0$
0)
#723000
b1100 0
1$
1)
#724000
0$
0)
#725000
b1101 0
1$
1)
#726000
0$
0)
#727000
b1110 0
1$
1)
#728000
0$
0)
#729000
b1111 0
1$
1)
#730000
0$
0)
#731000
b10000 0
1$
1)
#732000
0$
0)
#733000
b10001 0
1$
1)
#734000
0$
0)
#735000
b10010 0
1$
1)
#736000
0$
0)
#737000
b10011 0
1$
1)
#738000
0$
0)
#739000
b10100 0
1$
1)
#740000
0$
0)
#741000
b10101 0
1$
1)
#742000
0$
0)
#743000
b10110 0
1$
1)
#744000
0$
0)
#745000
b10111 0
1$
1)
#746000
0$
0)
#747000
b11000 0
1$
1)
#748000
0$
0)
#749000
b11001 0
1$
1)
#750000
0$
0)
#751000
b11010 0
1$
1)
#752000
0$
0)
#753000
b11011 0
1$
1)
#754000
0$
0)
#755000
b11100 0
1$
1)
#756000
0$
0)
#757000
b11101 0
1$
1)
#758000
0$
0)
#759000
b11110 0
1$
1)
#760000
0$
0)
#761000
b11111 0
1$
1)
#762000
0$
0)
#763000
b100000 0
1$
1)
#764000
0$
0)
#765000
b100001 0
1$
1)
#766000
0$
0)
#767000
b100010 0
1$
1)
#768000
0$
0)
#769000
b100011 0
1$
1)
#770000
0$
0)
#771000
b100100 0
1$
1)
#772000
0$
0)
#773000
b100101 0
1$
1)
#774000
0$
0)
#775000
b100110 0
1$
1)
#776000
0$
0)
#777000
b100111 0
1$
1)
#778000
0$
0)
#779000
b101000 0
1$
1)
#780000
0$
0)
#781000
b101001 0
1$
1)
#782000
0$
0)
#783000
b101010 0
1$
1)
#784000
0$
0)
#785000
b101011 0
1$
1)
#786000
0$
0)
#787000
b101100 0
1$
1)
#788000
0$
0)
#789000
b101101 0
1$
1)
#790000
0$
0)
#791000
b101110 0
1$
1)
#792000
0$
0)
#793000
b101111 0
1$
1)
#794000
0$
0)
#795000
b110000 0
1$
1)
#796000
0$
0)
#797000
b110001 0
1$
1)
#798000
0$
0)
#799000
01
0*
b0 0
1$
1)
#800000
0$
0)
#801000
b1 0
1$
1)
#802000
0$
0)
#803000
b10 0
1$
1)
#804000
0$
0)
#805000
b11 0
1$
1)
#806000
0$
0)
#807000
b100 0
1$
1)
